[{"12.10.2025": "Call22900", "instrumentType": "Index Options", "expiryDate": "14-Oct-2025", "optionType": "Call", "strikePrice": "22900", "openPrice": "-", "highPrice": "-", "lowPrice": "-", "closePrice": "-", "volume": 0, "name": "NIFTY14OCT2522900CE", "token": "42537", "SR Low -": "", "SR Low +": "", "SR PC -": "", "SR PC +": "", "SR High -": "", "SR High +": ""}, {"12.10.2025": "Put22950", "instrumentType": "Index Options", "expiryDate": "14-Oct-2025", "optionType": "Put", "strikePrice": "22950", "openPrice": "-", "highPrice": "-", "lowPrice": "-", "closePrice": "-", "volume": 0, "name": "NIFTY14OCT2522950PE", "token": "42540", "SR Low -": "", "SR Low +": "", "SR PC -": "", "SR PC +": "", "SR High -": "", "SR High +": ""}, {"12.10.2025": "Put23250", "instrumentType": "Index Options", "expiryDate": "14-Oct-2025", "optionType": "Put", "strikePrice": "23250", "openPrice": "-", "highPrice": "-", "lowPrice": "-", "closePrice": "-", "volume": 0, "name": "NIFTY14OCT2523250PE", "token": "42564", "SR Low -": "", "SR Low +": "", "SR PC -": "", "SR PC +": "", "SR High -": "", "SR High +": ""}, {"12.10.2025": "Put23350", "instrumentType": "Index Options", "expiryDate": "14-Oct-2025", "optionType": "Put", "strikePrice": "23350", "openPrice": "-", "highPrice": "-", "lowPrice": "-", "closePrice": "-", "volume": 0, "name": "NIFTY14OCT2523350PE", "token": "42576", "SR Low -": "", "SR Low +": "", "SR PC -": "", "SR PC +": "", "SR High -": "", "SR High +": ""}, {"12.10.2025": "Call23550", "instrumentType": "Index Options", "expiryDate": "14-Oct-2025", "optionType": "Call", "strikePrice": "23550", "openPrice": "-", "highPrice": "-", "lowPrice": "-", "closePrice": "-", "volume": 0, "name": "NIFTY14OCT2523550CE", "token": "42587", "SR Low -": "", "SR Low +": "", "SR PC -": "", "SR PC +": "", "SR High -": "", "SR High +": ""}, {"12.10.2025": "Call24150", "instrumentType": "Index Options", "expiryDate": "14-Oct-2025", "optionType": "Call", "strikePrice": "24150", "openPrice": "-", "highPrice": "-", "lowPrice": "-", "closePrice": "-", "volume": 0, "name": "NIFTY14OCT2524150CE", "token": "42617", "SR Low -": "", "SR Low +": "", "SR PC -": "", "SR PC +": "", "SR High -": "", "SR High +": ""}, {"12.10.2025": "Put24400", "instrumentType": "Index Options", "expiryDate": "14-Oct-2025", "optionType": "Put", "strikePrice": "24400", "openPrice": "-", "highPrice": "-", "lowPrice": "-", "closePrice": "-", "volume": 0, "name": "NIFTY14OCT2524400PE", "token": "42640", "SR Low -": "", "SR Low +": "", "SR PC -": "", "SR PC +": "", "SR High -": "", "SR High +": ""}, {"12.10.2025": "Call24950", "instrumentType": "Index Options", "expiryDate": "14-Oct-2025", "optionType": "Call", "strikePrice": "24950", "openPrice": "-", "highPrice": "-", "lowPrice": "-", "closePrice": "-", "volume": 0, "name": "NIFTY14OCT2524950CE", "token": "42671", "SR Low -": "", "SR Low +": "", "SR PC -": "", "SR PC +": "", "SR High -": "", "SR High +": ""}, {"12.10.2025": "Put25100", "instrumentType": "Index Options", "expiryDate": "14-Oct-2025", "optionType": "Put", "strikePrice": "25100", "openPrice": "-", "highPrice": "-", "lowPrice": "-", "closePrice": "-", "volume": 0, "name": "NIFTY14OCT2525100PE", "token": "42684", "SR Low -": "", "SR Low +": "", "SR PC -": "", "SR PC +": "", "SR High -": "", "SR High +": ""}, {"12.10.2025": "Call25450", "instrumentType": "Index Options", "expiryDate": "14-Oct-2025", "optionType": "Call", "strikePrice": "25450", "openPrice": "-", "highPrice": "-", "lowPrice": "-", "closePrice": "-", "volume": 0, "name": "NIFTY14OCT2525450CE", "token": "42705", "SR Low -": "", "SR Low +": "", "SR PC -": "", "SR PC +": "", "SR High -": "", "SR High +": ""}, {"12.10.2025": "Put25450", "instrumentType": "Index Options", "expiryDate": "14-Oct-2025", "optionType": "Put", "strikePrice": "25450", "openPrice": "-", "highPrice": "-", "lowPrice": "-", "closePrice": "-", "volume": 0, "name": "NIFTY14OCT2525450PE", "token": "42706", "SR Low -": "", "SR Low +": "", "SR PC -": "", "SR PC +": "", "SR High -": "", "SR High +": ""}, {"12.10.2025": "Call25500", "instrumentType": "Index Options", "expiryDate": "14-Oct-2025", "optionType": "Call", "strikePrice": "25500", "openPrice": "-", "highPrice": "-", "lowPrice": "-", "closePrice": "-", "volume": 0, "name": "NIFTY14OCT2525500CE", "token": "42707", "SR Low -": "", "SR Low +": "", "SR PC -": "", "SR PC +": "", "SR High -": "", "SR High +": ""}, {"12.10.2025": "Put25950", "instrumentType": "Index Options", "expiryDate": "14-Oct-2025", "optionType": "Put", "strikePrice": "25950", "openPrice": "-", "highPrice": "-", "lowPrice": "-", "closePrice": "-", "volume": 0, "name": "NIFTY14OCT2525950PE", "token": "42732", "SR Low -": "", "SR Low +": "", "SR PC -": "", "SR PC +": "", "SR High -": "", "SR High +": ""}, {"12.10.2025": "Call26200", "instrumentType": "Index Options", "expiryDate": "14-Oct-2025", "optionType": "Call", "strikePrice": "26200", "openPrice": "-", "highPrice": "-", "lowPrice": "-", "closePrice": "-", "volume": 0, "name": "NIFTY14OCT2526200CE", "token": "42743", "SR Low -": "", "SR Low +": "", "SR PC -": "", "SR PC +": "", "SR High -": "", "SR High +": ""}, {"12.10.2025": "Call26800", "instrumentType": "Index Options", "expiryDate": "14-Oct-2025", "optionType": "Call", "strikePrice": "26800", "openPrice": "-", "highPrice": "-", "lowPrice": "-", "closePrice": "-", "volume": 0, "name": "NIFTY14OCT2526800CE", "token": "42773", "SR Low -": "", "SR Low +": "", "SR PC -": "", "SR PC +": "", "SR High -": "", "SR High +": ""}, {"12.10.2025": "Call27000", "instrumentType": "Index Options", "expiryDate": "14-Oct-2025", "optionType": "Call", "strikePrice": "27000", "openPrice": "-", "highPrice": "-", "lowPrice": "-", "closePrice": "-", "volume": 0, "name": "NIFTY14OCT2527000CE", "token": "42783", "SR Low -": "", "SR Low +": "", "SR PC -": "", "SR PC +": "", "SR High -": "", "SR High +": ""}, {"12.10.2025": "Put23600", "instrumentType": "Index Options", "expiryDate": "14-Oct-2025", "optionType": "Put", "strikePrice": "23600", "openPrice": "-", "highPrice": "-", "lowPrice": "-", "closePrice": "-", "volume": 0, "name": "NIFTY14OCT2523600PE", "token": "42590", "SR Low -": "", "SR Low +": "", "SR PC -": "", "SR PC +": "", "SR High -": "", "SR High +": ""}, {"12.10.2025": "Call23650", "instrumentType": "Index Options", "expiryDate": "14-Oct-2025", "optionType": "Call", "strikePrice": "23650", "openPrice": "-", "highPrice": "-", "lowPrice": "-", "closePrice": "-", "volume": 0, "name": "NIFTY14OCT2523650CE", "token": "42591", "SR Low -": "", "SR Low +": "", "SR PC -": "", "SR PC +": "", "SR High -": "", "SR High +": ""}, {"12.10.2025": "Call23900", "instrumentType": "Index Options", "expiryDate": "14-Oct-2025", "optionType": "Call", "strikePrice": "23900", "openPrice": "-", "highPrice": "-", "lowPrice": "-", "closePrice": "-", "volume": 0, "name": "NIFTY14OCT2523900CE", "token": "42605", "SR Low -": "", "SR Low +": "", "SR PC -": "", "SR PC +": "", "SR High -": "", "SR High +": ""}, {"12.10.2025": "Call23950", "instrumentType": "Index Options", "expiryDate": "14-Oct-2025", "optionType": "Call", "strikePrice": "23950", "openPrice": "-", "highPrice": "-", "lowPrice": "-", "closePrice": "-", "volume": 0, "name": "NIFTY14OCT2523950CE", "token": "42607", "SR Low -": "", "SR Low +": "", "SR PC -": "", "SR PC +": "", "SR High -": "", "SR High +": ""}, {"12.10.2025": "Put24200", "instrumentType": "Index Options", "expiryDate": "14-Oct-2025", "optionType": "Put", "strikePrice": "24200", "openPrice": "-", "highPrice": "-", "lowPrice": "-", "closePrice": "-", "volume": 0, "name": "NIFTY14OCT2524200PE", "token": "42626", "SR Low -": "", "SR Low +": "", "SR PC -": "", "SR PC +": "", "SR High -": "", "SR High +": ""}, {"12.10.2025": "Call24250", "instrumentType": "Index Options", "expiryDate": "14-Oct-2025", "optionType": "Call", "strikePrice": "24250", "openPrice": "-", "highPrice": "-", "lowPrice": "-", "closePrice": "-", "volume": 0, "name": "NIFTY14OCT2524250CE", "token": "42627", "SR Low -": "", "SR Low +": "", "SR PC -": "", "SR PC +": "", "SR High -": "", "SR High +": ""}, {"12.10.2025": "Call24350", "instrumentType": "Index Options", "expiryDate": "14-Oct-2025", "optionType": "Call", "strikePrice": "24350", "openPrice": "-", "highPrice": "-", "lowPrice": "-", "closePrice": "-", "volume": 0, "name": "NIFTY14OCT2524350CE", "token": "42631", "SR Low -": "", "SR Low +": "", "SR PC -": "", "SR PC +": "", "SR High -": "", "SR High +": ""}, {"12.10.2025": "Put24500", "instrumentType": "Index Options", "expiryDate": "14-Oct-2025", "optionType": "Put", "strikePrice": "24500", "openPrice": "-", "highPrice": "-", "lowPrice": "-", "closePrice": "-", "volume": 0, "name": "NIFTY14OCT2524500PE", "token": "42646", "SR Low -": "", "SR Low +": "", "SR PC -": "", "SR PC +": "", "SR High -": "", "SR High +": ""}, {"12.10.2025": "Call25050", "instrumentType": "Index Options", "expiryDate": "14-Oct-2025", "optionType": "Call", "strikePrice": "25050", "openPrice": "-", "highPrice": "-", "lowPrice": "-", "closePrice": "-", "volume": 0, "name": "NIFTY14OCT2525050CE", "token": "42677", "SR Low -": "", "SR Low +": "", "SR PC -": "", "SR PC +": "", "SR High -": "", "SR High +": ""}, {"12.10.2025": "Put25200", "instrumentType": "Index Options", "expiryDate": "14-Oct-2025", "optionType": "Put", "strikePrice": "25200", "openPrice": "-", "highPrice": "-", "lowPrice": "-", "closePrice": "-", "volume": 0, "name": "NIFTY14OCT2525200PE", "token": "42690", "SR Low -": "", "SR Low +": "", "SR PC -": "", "SR PC +": "", "SR High -": "", "SR High +": ""}, {"12.10.2025": "Put26150", "instrumentType": "Index Options", "expiryDate": "14-Oct-2025", "optionType": "Put", "strikePrice": "26150", "openPrice": "-", "highPrice": "-", "lowPrice": "-", "closePrice": "-", "volume": 0, "name": "NIFTY14OCT2526150PE", "token": "42742", "SR Low -": "", "SR Low +": "", "SR PC -": "", "SR PC +": "", "SR High -": "", "SR High +": ""}, {"12.10.2025": "Call25550", "instrumentType": "Index Options", "expiryDate": "14-Oct-2025", "optionType": "Call", "strikePrice": "25550", "openPrice": "-", "highPrice": "-", "lowPrice": "-", "closePrice": "-", "volume": 0, "name": "NIFTY14OCT2525550CE", "token": "42711", "SR Low -": "", "SR Low +": "", "SR PC -": "", "SR PC +": "", "SR High -": "", "SR High +": ""}, {"12.10.2025": "Call25700", "instrumentType": "Index Options", "expiryDate": "14-Oct-2025", "optionType": "Call", "strikePrice": "25700", "openPrice": "-", "highPrice": "-", "lowPrice": "-", "closePrice": "-", "volume": 0, "name": "NIFTY14OCT2525700CE", "token": "42717", "SR Low -": "", "SR Low +": "", "SR PC -": "", "SR PC +": "", "SR High -": "", "SR High +": ""}, {"12.10.2025": "Call26000", "instrumentType": "Index Options", "expiryDate": "14-Oct-2025", "optionType": "Call", "strikePrice": "26000", "openPrice": "-", "highPrice": "-", "lowPrice": "-", "closePrice": "-", "volume": 0, "name": "NIFTY14OCT2526000CE", "token": "42733", "SR Low -": "", "SR Low +": "", "SR PC -": "", "SR PC +": "", "SR High -": "", "SR High +": ""}, {"12.10.2025": "Call26300", "instrumentType": "Index Options", "expiryDate": "14-Oct-2025", "optionType": "Call", "strikePrice": "26300", "openPrice": "-", "highPrice": "-", "lowPrice": "-", "closePrice": "-", "volume": 0, "name": "NIFTY14OCT2526300CE", "token": "42749", "SR Low -": "", "SR Low +": "", "SR PC -": "", "SR PC +": "", "SR High -": "", "SR High +": ""}, {"12.10.2025": "Put26400", "instrumentType": "Index Options", "expiryDate": "14-Oct-2025", "optionType": "Put", "strikePrice": "26400", "openPrice": "-", "highPrice": "-", "lowPrice": "-", "closePrice": "-", "volume": 0, "name": "NIFTY14OCT2526400PE", "token": "42756", "SR Low -": "", "SR Low +": "", "SR PC -": "", "SR PC +": "", "SR High -": "", "SR High +": ""}, {"12.10.2025": "Call26500", "instrumentType": "Index Options", "expiryDate": "14-Oct-2025", "optionType": "Call", "strikePrice": "26500", "openPrice": "-", "highPrice": "-", "lowPrice": "-", "closePrice": "-", "volume": 0, "name": "NIFTY14OCT2526500CE", "token": "42759", "SR Low -": "", "SR Low +": "", "SR PC -": "", "SR PC +": "", "SR High -": "", "SR High +": ""}, {"12.10.2025": "Put26550", "instrumentType": "Index Options", "expiryDate": "14-Oct-2025", "optionType": "Put", "strikePrice": "26550", "openPrice": "-", "highPrice": "-", "lowPrice": "-", "closePrice": "-", "volume": 0, "name": "NIFTY14OCT2526550PE", "token": "42762", "SR Low -": "", "SR Low +": "", "SR PC -": "", "SR PC +": "", "SR High -": "", "SR High +": ""}, {"12.10.2025": "Call26600", "instrumentType": "Index Options", "expiryDate": "14-Oct-2025", "optionType": "Call", "strikePrice": "26600", "openPrice": "-", "highPrice": "-", "lowPrice": "-", "closePrice": "-", "volume": 0, "name": "NIFTY14OCT2526600CE", "token": "42763", "SR Low -": "", "SR Low +": "", "SR PC -": "", "SR PC +": "", "SR High -": "", "SR High +": ""}, {"12.10.2025": "Put26700", "instrumentType": "Index Options", "expiryDate": "14-Oct-2025", "optionType": "Put", "strikePrice": "26700", "openPrice": "-", "highPrice": "-", "lowPrice": "-", "closePrice": "-", "volume": 0, "name": "NIFTY14OCT2526700PE", "token": "42770", "SR Low -": "", "SR Low +": "", "SR PC -": "", "SR PC +": "", "SR High -": "", "SR High +": ""}, {"12.10.2025": "Call23100", "instrumentType": "Index Options", "expiryDate": "14-Oct-2025", "optionType": "Call", "strikePrice": "23100", "openPrice": "-", "highPrice": "-", "lowPrice": "-", "closePrice": "-", "volume": 0, "name": "NIFTY14OCT2523100CE", "token": "42547", "SR Low -": "", "SR Low +": "", "SR PC -": "", "SR PC +": "", "SR High -": "", "SR High +": ""}, {"12.10.2025": "Put23100", "instrumentType": "Index Options", "expiryDate": "14-Oct-2025", "optionType": "Put", "strikePrice": "23100", "openPrice": "-", "highPrice": "-", "lowPrice": "-", "closePrice": "-", "volume": 0, "name": "NIFTY14OCT2523100PE", "token": "42549", "SR Low -": "", "SR Low +": "", "SR PC -": "", "SR PC +": "", "SR High -": "", "SR High +": ""}, {"12.10.2025": "Put23150", "instrumentType": "Index Options", "expiryDate": "14-Oct-2025", "optionType": "Put", "strikePrice": "23150", "openPrice": "-", "highPrice": "-", "lowPrice": "-", "closePrice": "-", "volume": 0, "name": "NIFTY14OCT2523150PE", "token": "42553", "SR Low -": "", "SR Low +": "", "SR PC -": "", "SR PC +": "", "SR High -": "", "SR High +": ""}, {"12.10.2025": "Call23200", "instrumentType": "Index Options", "expiryDate": "14-Oct-2025", "optionType": "Call", "strikePrice": "23200", "openPrice": "-", "highPrice": "-", "lowPrice": "-", "closePrice": "-", "volume": 0, "name": "NIFTY14OCT2523200CE", "token": "42554", "SR Low -": "", "SR Low +": "", "SR PC -": "", "SR PC +": "", "SR High -": "", "SR High +": ""}, {"12.10.2025": "Put23500", "instrumentType": "Index Options", "expiryDate": "14-Oct-2025", "optionType": "Put", "strikePrice": "23500", "openPrice": "-", "highPrice": "-", "lowPrice": "-", "closePrice": "-", "volume": 0, "name": "NIFTY14OCT2523500PE", "token": "42586", "SR Low -": "", "SR Low +": "", "SR PC -": "", "SR PC +": "", "SR High -": "", "SR High +": ""}, {"12.10.2025": "Put23550", "instrumentType": "Index Options", "expiryDate": "14-Oct-2025", "optionType": "Put", "strikePrice": "23550", "openPrice": "-", "highPrice": "-", "lowPrice": "-", "closePrice": "-", "volume": 0, "name": "NIFTY14OCT2523550PE", "token": "42588", "SR Low -": "", "SR Low +": "", "SR PC -": "", "SR PC +": "", "SR High -": "", "SR High +": ""}, {"12.10.2025": "Call23750", "instrumentType": "Index Options", "expiryDate": "14-Oct-2025", "optionType": "Call", "strikePrice": "23750", "openPrice": "-", "highPrice": "-", "lowPrice": "-", "closePrice": "-", "volume": 0, "name": "NIFTY14OCT2523750CE", "token": "42597", "SR Low -": "", "SR Low +": "", "SR PC -": "", "SR PC +": "", "SR High -": "", "SR High +": ""}, {"12.10.2025": "Put23750", "instrumentType": "Index Options", "expiryDate": "14-Oct-2025", "optionType": "Put", "strikePrice": "23750", "openPrice": "-", "highPrice": "-", "lowPrice": "-", "closePrice": "-", "volume": 0, "name": "NIFTY14OCT2523750PE", "token": "42600", "SR Low -": "", "SR Low +": "", "SR PC -": "", "SR PC +": "", "SR High -": "", "SR High +": ""}, {"12.10.2025": "Put23850", "instrumentType": "Index Options", "expiryDate": "14-Oct-2025", "optionType": "Put", "strikePrice": "23850", "openPrice": "-", "highPrice": "-", "lowPrice": "-", "closePrice": "-", "volume": 0, "name": "NIFTY14OCT2523850PE", "token": "42604", "SR Low -": "", "SR Low +": "", "SR PC -": "", "SR PC +": "", "SR High -": "", "SR High +": ""}, {"12.10.2025": "Call24400", "instrumentType": "Index Options", "expiryDate": "14-Oct-2025", "optionType": "Call", "strikePrice": "24400", "openPrice": "-", "highPrice": "-", "lowPrice": "-", "closePrice": "-", "volume": 0, "name": "NIFTY14OCT2524400CE", "token": "42633", "SR Low -": "", "SR Low +": "", "SR PC -": "", "SR PC +": "", "SR High -": "", "SR High +": ""}, {"12.10.2025": "Call24750", "instrumentType": "Index Options", "expiryDate": "14-Oct-2025", "optionType": "Call", "strikePrice": "24750", "openPrice": "-", "highPrice": "-", "lowPrice": "-", "closePrice": "-", "volume": 0, "name": "NIFTY14OCT2524750CE", "token": "42657", "SR Low -": "", "SR Low +": "", "SR PC -": "", "SR PC +": "", "SR High -": "", "SR High +": ""}, {"12.10.2025": "Put24900", "instrumentType": "Index Options", "expiryDate": "14-Oct-2025", "optionType": "Put", "strikePrice": "24900", "openPrice": "-", "highPrice": "-", "lowPrice": "-", "closePrice": "-", "volume": 0, "name": "NIFTY14OCT2524900PE", "token": "42670", "SR Low -": "", "SR Low +": "", "SR PC -": "", "SR PC +": "", "SR High -": "", "SR High +": ""}, {"12.10.2025": "Put25800", "instrumentType": "Index Options", "expiryDate": "14-Oct-2025", "optionType": "Put", "strikePrice": "25800", "openPrice": "-", "highPrice": "-", "lowPrice": "-", "closePrice": "-", "volume": 0, "name": "NIFTY14OCT2525800PE", "token": "42722", "SR Low -": "", "SR Low +": "", "SR PC -": "", "SR PC +": "", "SR High -": "", "SR High +": ""}, {"12.10.2025": "Put26000", "instrumentType": "Index Options", "expiryDate": "14-Oct-2025", "optionType": "Put", "strikePrice": "26000", "openPrice": "-", "highPrice": "-", "lowPrice": "-", "closePrice": "-", "volume": 0, "name": "NIFTY14OCT2526000PE", "token": "42734", "SR Low -": "", "SR Low +": "", "SR PC -": "", "SR PC +": "", "SR High -": "", "SR High +": ""}, {"12.10.2025": "Put26250", "instrumentType": "Index Options", "expiryDate": "14-Oct-2025", "optionType": "Put", "strikePrice": "26250", "openPrice": "-", "highPrice": "-", "lowPrice": "-", "closePrice": "-", "volume": 0, "name": "NIFTY14OCT2526250PE", "token": "42748", "SR Low -": "", "SR Low +": "", "SR PC -": "", "SR PC +": "", "SR High -": "", "SR High +": ""}, {"12.10.2025": "Call26400", "instrumentType": "Index Options", "expiryDate": "14-Oct-2025", "optionType": "Call", "strikePrice": "26400", "openPrice": "-", "highPrice": "-", "lowPrice": "-", "closePrice": "-", "volume": 0, "name": "NIFTY14OCT2526400CE", "token": "42755", "SR Low -": "", "SR Low +": "", "SR PC -": "", "SR PC +": "", "SR High -": "", "SR High +": ""}, {"12.10.2025": "Put26850", "instrumentType": "Index Options", "expiryDate": "14-Oct-2025", "optionType": "Put", "strikePrice": "26850", "openPrice": "-", "highPrice": "-", "lowPrice": "-", "closePrice": "-", "volume": 0, "name": "NIFTY14OCT2526850PE", "token": "42776", "SR Low -": "", "SR Low +": "", "SR PC -": "", "SR PC +": "", "SR High -": "", "SR High +": ""}, {"12.10.2025": "Put22900", "instrumentType": "Index Options", "expiryDate": "14-Oct-2025", "optionType": "Put", "strikePrice": "22900", "openPrice": "-", "highPrice": "-", "lowPrice": "-", "closePrice": "-", "volume": 0, "name": "NIFTY14OCT2522900PE", "token": "42538", "SR Low -": "", "SR Low +": "", "SR PC -": "", "SR PC +": "", "SR High -": "", "SR High +": ""}, {"12.10.2025": "Put23950", "instrumentType": "Index Options", "expiryDate": "14-Oct-2025", "optionType": "Put", "strikePrice": "23950", "openPrice": "-", "highPrice": "-", "lowPrice": "-", "closePrice": "-", "volume": 0, "name": "NIFTY14OCT2523950PE", "token": "42608", "SR Low -": "", "SR Low +": "", "SR PC -": "", "SR PC +": "", "SR High -": "", "SR High +": ""}, {"12.10.2025": "Call24300", "instrumentType": "Index Options", "expiryDate": "14-Oct-2025", "optionType": "Call", "strikePrice": "24300", "openPrice": "-", "highPrice": "-", "lowPrice": "-", "closePrice": "-", "volume": 0, "name": "NIFTY14OCT2524300CE", "token": "42629", "SR Low -": "", "SR Low +": "", "SR PC -": "", "SR PC +": "", "SR High -": "", "SR High +": ""}, {"12.10.2025": "Put24350", "instrumentType": "Index Options", "expiryDate": "14-Oct-2025", "optionType": "Put", "strikePrice": "24350", "openPrice": "-", "highPrice": "-", "lowPrice": "-", "closePrice": "-", "volume": 0, "name": "NIFTY14OCT2524350PE", "token": "42632", "SR Low -": "", "SR Low +": "", "SR PC -": "", "SR PC +": "", "SR High -": "", "SR High +": ""}, {"12.10.2025": "Call24500", "instrumentType": "Index Options", "expiryDate": "14-Oct-2025", "optionType": "Call", "strikePrice": "24500", "openPrice": "-", "highPrice": "-", "lowPrice": "-", "closePrice": "-", "volume": 0, "name": "NIFTY14OCT2524500CE", "token": "42645", "SR Low -": "", "SR Low +": "", "SR PC -": "", "SR PC +": "", "SR High -": "", "SR High +": ""}, {"12.10.2025": "Put24550", "instrumentType": "Index Options", "expiryDate": "14-Oct-2025", "optionType": "Put", "strikePrice": "24550", "openPrice": "-", "highPrice": "-", "lowPrice": "-", "closePrice": "-", "volume": 0, "name": "NIFTY14OCT2524550PE", "token": "42648", "SR Low -": "", "SR Low +": "", "SR PC -": "", "SR PC +": "", "SR High -": "", "SR High +": ""}, {"12.10.2025": "Call24600", "instrumentType": "Index Options", "expiryDate": "14-Oct-2025", "optionType": "Call", "strikePrice": "24600", "openPrice": "-", "highPrice": "-", "lowPrice": "-", "closePrice": "-", "volume": 0, "name": "NIFTY14OCT2524600CE", "token": "42649", "SR Low -": "", "SR Low +": "", "SR PC -": "", "SR PC +": "", "SR High -": "", "SR High +": ""}, {"12.10.2025": "Call25000", "instrumentType": "Index Options", "expiryDate": "14-Oct-2025", "optionType": "Call", "strikePrice": "25000", "openPrice": "-", "highPrice": "-", "lowPrice": "-", "closePrice": "-", "volume": 0, "name": "NIFTY14OCT2525000CE", "token": "42673", "SR Low -": "", "SR Low +": "", "SR PC -": "", "SR PC +": "", "SR High -": "", "SR High +": ""}, {"12.10.2025": "Call25150", "instrumentType": "Index Options", "expiryDate": "14-Oct-2025", "optionType": "Call", "strikePrice": "25150", "openPrice": "-", "highPrice": "-", "lowPrice": "-", "closePrice": "-", "volume": 0, "name": "NIFTY14OCT2525150CE", "token": "42685", "SR Low -": "", "SR Low +": "", "SR PC -": "", "SR PC +": "", "SR High -": "", "SR High +": ""}, {"12.10.2025": "Put25250", "instrumentType": "Index Options", "expiryDate": "14-Oct-2025", "optionType": "Put", "strikePrice": "25250", "openPrice": "-", "highPrice": "-", "lowPrice": "-", "closePrice": "-", "volume": 0, "name": "NIFTY14OCT2525250PE", "token": "42692", "SR Low -": "", "SR Low +": "", "SR PC -": "", "SR PC +": "", "SR High -": "", "SR High +": ""}, {"12.10.2025": "Call25650", "instrumentType": "Index Options", "expiryDate": "14-Oct-2025", "optionType": "Call", "strikePrice": "25650", "openPrice": "-", "highPrice": "-", "lowPrice": "-", "closePrice": "-", "volume": 0, "name": "NIFTY14OCT2525650CE", "token": "42715", "SR Low -": "", "SR Low +": "", "SR PC -": "", "SR PC +": "", "SR High -": "", "SR High +": ""}, {"12.10.2025": "Put26450", "instrumentType": "Index Options", "expiryDate": "14-Oct-2025", "optionType": "Put", "strikePrice": "26450", "openPrice": "-", "highPrice": "-", "lowPrice": "-", "closePrice": "-", "volume": 0, "name": "NIFTY14OCT2526450PE", "token": "42758", "SR Low -": "", "SR Low +": "", "SR PC -": "", "SR PC +": "", "SR High -": "", "SR High +": ""}, {"12.10.2025": "Call26550", "instrumentType": "Index Options", "expiryDate": "14-Oct-2025", "optionType": "Call", "strikePrice": "26550", "openPrice": "-", "highPrice": "-", "lowPrice": "-", "closePrice": "-", "volume": 0, "name": "NIFTY14OCT2526550CE", "token": "42761", "SR Low -": "", "SR Low +": "", "SR PC -": "", "SR PC +": "", "SR High -": "", "SR High +": ""}, {"12.10.2025": "Put26950", "instrumentType": "Index Options", "expiryDate": "14-Oct-2025", "optionType": "Put", "strikePrice": "26950", "openPrice": "-", "highPrice": "-", "lowPrice": "-", "closePrice": "-", "volume": 0, "name": "NIFTY14OCT2526950PE", "token": "42782", "SR Low -": "", "SR Low +": "", "SR PC -": "", "SR PC +": "", "SR High -": "", "SR High +": ""}, {"12.10.2025": "Put27100", "instrumentType": "Index Options", "expiryDate": "14-Oct-2025", "optionType": "Put", "strikePrice": "27100", "openPrice": "-", "highPrice": "-", "lowPrice": "-", "closePrice": "-", "volume": 0, "name": "NIFTY14OCT2527100PE", "token": "42792", "SR Low -": "", "SR Low +": "", "SR PC -": "", "SR PC +": "", "SR High -": "", "SR High +": ""}, {"12.10.2025": "Put22850", "instrumentType": "Index Options", "expiryDate": "14-Oct-2025", "optionType": "Put", "strikePrice": "22850", "openPrice": "-", "highPrice": "-", "lowPrice": "-", "closePrice": "-", "volume": 0, "name": "NIFTY14OCT2522850PE", "token": "42536", "SR Low -": "", "SR Low +": "", "SR PC -": "", "SR PC +": "", "SR High -": "", "SR High +": ""}, {"12.10.2025": "Put23000", "instrumentType": "Index Options", "expiryDate": "14-Oct-2025", "optionType": "Put", "strikePrice": "23000", "openPrice": "-", "highPrice": "-", "lowPrice": "-", "closePrice": "-", "volume": 0, "name": "NIFTY14OCT2523000PE", "token": "42542", "SR Low -": "", "SR Low +": "", "SR PC -": "", "SR PC +": "", "SR High -": "", "SR High +": ""}, {"12.10.2025": "Call23050", "instrumentType": "Index Options", "expiryDate": "14-Oct-2025", "optionType": "Call", "strikePrice": "23050", "openPrice": "-", "highPrice": "-", "lowPrice": "-", "closePrice": "-", "volume": 0, "name": "NIFTY14OCT2523050CE", "token": "42543", "SR Low -": "", "SR Low +": "", "SR PC -": "", "SR PC +": "", "SR High -": "", "SR High +": ""}, {"12.10.2025": "Call23300", "instrumentType": "Index Options", "expiryDate": "14-Oct-2025", "optionType": "Call", "strikePrice": "23300", "openPrice": "-", "highPrice": "-", "lowPrice": "-", "closePrice": "-", "volume": 0, "name": "NIFTY14OCT2523300CE", "token": "42565", "SR Low -": "", "SR Low +": "", "SR PC -": "", "SR PC +": "", "SR High -": "", "SR High +": ""}, {"12.10.2025": "Put23400", "instrumentType": "Index Options", "expiryDate": "14-Oct-2025", "optionType": "Put", "strikePrice": "23400", "openPrice": "-", "highPrice": "-", "lowPrice": "-", "closePrice": "-", "volume": 0, "name": "NIFTY14OCT2523400PE", "token": "42582", "SR Low -": "", "SR Low +": "", "SR PC -": "", "SR PC +": "", "SR High -": "", "SR High +": ""}, {"12.10.2025": "Call23500", "instrumentType": "Index Options", "expiryDate": "14-Oct-2025", "optionType": "Call", "strikePrice": "23500", "openPrice": "-", "highPrice": "-", "lowPrice": "-", "closePrice": "-", "volume": 0, "name": "NIFTY14OCT2523500CE", "token": "42585", "SR Low -": "", "SR Low +": "", "SR PC -": "", "SR PC +": "", "SR High -": "", "SR High +": ""}, {"12.10.2025": "Call23850", "instrumentType": "Index Options", "expiryDate": "14-Oct-2025", "optionType": "Call", "strikePrice": "23850", "openPrice": "-", "highPrice": "-", "lowPrice": "-", "closePrice": "-", "volume": 0, "name": "NIFTY14OCT2523850CE", "token": "42603", "SR Low -": "", "SR Low +": "", "SR PC -": "", "SR PC +": "", "SR High -": "", "SR High +": ""}, {"12.10.2025": "Put24050", "instrumentType": "Index Options", "expiryDate": "14-Oct-2025", "optionType": "Put", "strikePrice": "24050", "openPrice": "-", "highPrice": "-", "lowPrice": "-", "closePrice": "-", "volume": 0, "name": "NIFTY14OCT2524050PE", "token": "42614", "SR Low -": "", "SR Low +": "", "SR PC -": "", "SR PC +": "", "SR High -": "", "SR High +": ""}, {"12.10.2025": "Call24200", "instrumentType": "Index Options", "expiryDate": "14-Oct-2025", "optionType": "Call", "strikePrice": "24200", "openPrice": "-", "highPrice": "-", "lowPrice": "-", "closePrice": "-", "volume": 0, "name": "NIFTY14OCT2524200CE", "token": "42622", "SR Low -": "", "SR Low +": "", "SR PC -": "", "SR PC +": "", "SR High -": "", "SR High +": ""}, {"12.10.2025": "Call24450", "instrumentType": "Index Options", "expiryDate": "14-Oct-2025", "optionType": "Call", "strikePrice": "24450", "openPrice": "-", "highPrice": "-", "lowPrice": "-", "closePrice": "-", "volume": 0, "name": "NIFTY14OCT2524450CE", "token": "42641", "SR Low -": "", "SR Low +": "", "SR PC -": "", "SR PC +": "", "SR High -": "", "SR High +": ""}, {"12.10.2025": "Call24550", "instrumentType": "Index Options", "expiryDate": "14-Oct-2025", "optionType": "Call", "strikePrice": "24550", "openPrice": "-", "highPrice": "-", "lowPrice": "-", "closePrice": "-", "volume": 0, "name": "NIFTY14OCT2524550CE", "token": "42647", "SR Low -": "", "SR Low +": "", "SR PC -": "", "SR PC +": "", "SR High -": "", "SR High +": ""}, {"12.10.2025": "Put24600", "instrumentType": "Index Options", "expiryDate": "14-Oct-2025", "optionType": "Put", "strikePrice": "24600", "openPrice": "-", "highPrice": "-", "lowPrice": "-", "closePrice": "-", "volume": 0, "name": "NIFTY14OCT2524600PE", "token": "42650", "SR Low -": "", "SR Low +": "", "SR PC -": "", "SR PC +": "", "SR High -": "", "SR High +": ""}, {"12.10.2025": "Put24700", "instrumentType": "Index Options", "expiryDate": "14-Oct-2025", "optionType": "Put", "strikePrice": "24700", "openPrice": "-", "highPrice": "-", "lowPrice": "-", "closePrice": "-", "volume": 0, "name": "NIFTY14OCT2524700PE", "token": "42656", "SR Low -": "", "SR Low +": "", "SR PC -": "", "SR PC +": "", "SR High -": "", "SR High +": ""}, {"12.10.2025": "Call24800", "instrumentType": "Index Options", "expiryDate": "14-Oct-2025", "optionType": "Call", "strikePrice": "24800", "openPrice": "-", "highPrice": "-", "lowPrice": "-", "closePrice": "-", "volume": 0, "name": "NIFTY14OCT2524800CE", "token": "42661", "SR Low -": "", "SR Low +": "", "SR PC -": "", "SR PC +": "", "SR High -": "", "SR High +": ""}, {"12.10.2025": "Put25000", "instrumentType": "Index Options", "expiryDate": "14-Oct-2025", "optionType": "Put", "strikePrice": "25000", "openPrice": "-", "highPrice": "-", "lowPrice": "-", "closePrice": "-", "volume": 0, "name": "NIFTY14OCT2525000PE", "token": "42676", "SR Low -": "", "SR Low +": "", "SR PC -": "", "SR PC +": "", "SR High -": "", "SR High +": ""}, {"12.10.2025": "Call25350", "instrumentType": "Index Options", "expiryDate": "14-Oct-2025", "optionType": "Call", "strikePrice": "25350", "openPrice": "-", "highPrice": "-", "lowPrice": "-", "closePrice": "-", "volume": 0, "name": "NIFTY14OCT2525350CE", "token": "42695", "SR Low -": "", "SR Low +": "", "SR PC -": "", "SR PC +": "", "SR High -": "", "SR High +": ""}, {"12.10.2025": "Put25350", "instrumentType": "Index Options", "expiryDate": "14-Oct-2025", "optionType": "Put", "strikePrice": "25350", "openPrice": "-", "highPrice": "-", "lowPrice": "-", "closePrice": "-", "volume": 0, "name": "NIFTY14OCT2525350PE", "token": "42702", "SR Low -": "", "SR Low +": "", "SR PC -": "", "SR PC +": "", "SR High -": "", "SR High +": ""}, {"12.10.2025": "Put25600", "instrumentType": "Index Options", "expiryDate": "14-Oct-2025", "optionType": "Put", "strikePrice": "25600", "openPrice": "-", "highPrice": "-", "lowPrice": "-", "closePrice": "-", "volume": 0, "name": "NIFTY14OCT2525600PE", "token": "42714", "SR Low -": "", "SR Low +": "", "SR PC -": "", "SR PC +": "", "SR High -": "", "SR High +": ""}, {"12.10.2025": "Put25650", "instrumentType": "Index Options", "expiryDate": "14-Oct-2025", "optionType": "Put", "strikePrice": "25650", "openPrice": "-", "highPrice": "-", "lowPrice": "-", "closePrice": "-", "volume": 0, "name": "NIFTY14OCT2525650PE", "token": "42716", "SR Low -": "", "SR Low +": "", "SR PC -": "", "SR PC +": "", "SR High -": "", "SR High +": ""}, {"12.10.2025": "Call25750", "instrumentType": "Index Options", "expiryDate": "14-Oct-2025", "optionType": "Call", "strikePrice": "25750", "openPrice": "-", "highPrice": "-", "lowPrice": "-", "closePrice": "-", "volume": 0, "name": "NIFTY14OCT2525750CE", "token": "42719", "SR Low -": "", "SR Low +": "", "SR PC -": "", "SR PC +": "", "SR High -": "", "SR High +": ""}, {"12.10.2025": "Put26100", "instrumentType": "Index Options", "expiryDate": "14-Oct-2025", "optionType": "Put", "strikePrice": "26100", "openPrice": "-", "highPrice": "-", "lowPrice": "-", "closePrice": "-", "volume": 0, "name": "NIFTY14OCT2526100PE", "token": "42740", "SR Low -": "", "SR Low +": "", "SR PC -": "", "SR PC +": "", "SR High -": "", "SR High +": ""}, {"12.10.2025": "Call26150", "instrumentType": "Index Options", "expiryDate": "14-Oct-2025", "optionType": "Call", "strikePrice": "26150", "openPrice": "-", "highPrice": "-", "lowPrice": "-", "closePrice": "-", "volume": 0, "name": "NIFTY14OCT2526150CE", "token": "42741", "SR Low -": "", "SR Low +": "", "SR PC -": "", "SR PC +": "", "SR High -": "", "SR High +": ""}, {"12.10.2025": "Call26450", "instrumentType": "Index Options", "expiryDate": "14-Oct-2025", "optionType": "Call", "strikePrice": "26450", "openPrice": "-", "highPrice": "-", "lowPrice": "-", "closePrice": "-", "volume": 0, "name": "NIFTY14OCT2526450CE", "token": "42757", "SR Low -": "", "SR Low +": "", "SR PC -": "", "SR PC +": "", "SR High -": "", "SR High +": ""}, {"12.10.2025": "Put26650", "instrumentType": "Index Options", "expiryDate": "14-Oct-2025", "optionType": "Put", "strikePrice": "26650", "openPrice": "-", "highPrice": "-", "lowPrice": "-", "closePrice": "-", "volume": 0, "name": "NIFTY14OCT2526650PE", "token": "42768", "SR Low -": "", "SR Low +": "", "SR PC -": "", "SR PC +": "", "SR High -": "", "SR High +": ""}, {"12.10.2025": "Call26850", "instrumentType": "Index Options", "expiryDate": "14-Oct-2025", "optionType": "Call", "strikePrice": "26850", "openPrice": "-", "highPrice": "-", "lowPrice": "-", "closePrice": "-", "volume": 0, "name": "NIFTY14OCT2526850CE", "token": "42775", "SR Low -": "", "SR Low +": "", "SR PC -": "", "SR PC +": "", "SR High -": "", "SR High +": ""}, {"12.10.2025": "Call26900", "instrumentType": "Index Options", "expiryDate": "14-Oct-2025", "optionType": "Call", "strikePrice": "26900", "openPrice": "-", "highPrice": "-", "lowPrice": "-", "closePrice": "-", "volume": 0, "name": "NIFTY14OCT2526900CE", "token": "42777", "SR Low -": "", "SR Low +": "", "SR PC -": "", "SR PC +": "", "SR High -": "", "SR High +": ""}, {"12.10.2025": "Call27150", "instrumentType": "Index Options", "expiryDate": "14-Oct-2025", "optionType": "Call", "strikePrice": "27150", "openPrice": "-", "highPrice": "-", "lowPrice": "-", "closePrice": "-", "volume": 0, "name": "NIFTY14OCT2527150CE", "token": "42793", "SR Low -": "", "SR Low +": "", "SR PC -": "", "SR PC +": "", "SR High -": "", "SR High +": ""}, {"12.10.2025": "Put27150", "instrumentType": "Index Options", "expiryDate": "14-Oct-2025", "optionType": "Put", "strikePrice": "27150", "openPrice": "-", "highPrice": "-", "lowPrice": "-", "closePrice": "-", "volume": 0, "name": "NIFTY14OCT2527150PE", "token": "42796", "SR Low -": "", "SR Low +": "", "SR PC -": "", "SR PC +": "", "SR High -": "", "SR High +": ""}, {"12.10.2025": "Put23200", "instrumentType": "Index Options", "expiryDate": "14-Oct-2025", "optionType": "Put", "strikePrice": "23200", "openPrice": "-", "highPrice": "-", "lowPrice": "-", "closePrice": "-", "volume": 0, "name": "NIFTY14OCT2523200PE", "token": "42557", "SR Low -": "", "SR Low +": "", "SR PC -": "", "SR PC +": "", "SR High -": "", "SR High +": ""}, {"12.10.2025": "Call23600", "instrumentType": "Index Options", "expiryDate": "14-Oct-2025", "optionType": "Call", "strikePrice": "23600", "openPrice": "-", "highPrice": "-", "lowPrice": "-", "closePrice": "-", "volume": 0, "name": "NIFTY14OCT2523600CE", "token": "42589", "SR Low -": "", "SR Low +": "", "SR PC -": "", "SR PC +": "", "SR High -": "", "SR High +": ""}, {"12.10.2025": "Put23700", "instrumentType": "Index Options", "expiryDate": "14-Oct-2025", "optionType": "Put", "strikePrice": "23700", "openPrice": "-", "highPrice": "-", "lowPrice": "-", "closePrice": "-", "volume": 0, "name": "NIFTY14OCT2523700PE", "token": "42596", "SR Low -": "", "SR Low +": "", "SR PC -": "", "SR PC +": "", "SR High -": "", "SR High +": ""}, {"12.10.2025": "Put23800", "instrumentType": "Index Options", "expiryDate": "14-Oct-2025", "optionType": "Put", "strikePrice": "23800", "openPrice": "-", "highPrice": "-", "lowPrice": "-", "closePrice": "-", "volume": 0, "name": "NIFTY14OCT2523800PE", "token": "42602", "SR Low -": "", "SR Low +": "", "SR PC -": "", "SR PC +": "", "SR High -": "", "SR High +": ""}, {"12.10.2025": "Put24000", "instrumentType": "Index Options", "expiryDate": "14-Oct-2025", "optionType": "Put", "strikePrice": "24000", "openPrice": "-", "highPrice": "-", "lowPrice": "-", "closePrice": "-", "volume": 0, "name": "NIFTY14OCT2524000PE", "token": "42612", "SR Low -": "", "SR Low +": "", "SR PC -": "", "SR PC +": "", "SR High -": "", "SR High +": ""}, {"12.10.2025": "Call24050", "instrumentType": "Index Options", "expiryDate": "14-Oct-2025", "optionType": "Call", "strikePrice": "24050", "openPrice": "-", "highPrice": "-", "lowPrice": "-", "closePrice": "-", "volume": 0, "name": "NIFTY14OCT2524050CE", "token": "42613", "SR Low -": "", "SR Low +": "", "SR PC -": "", "SR PC +": "", "SR High -": "", "SR High +": ""}, {"12.10.2025": "Put24100", "instrumentType": "Index Options", "expiryDate": "14-Oct-2025", "optionType": "Put", "strikePrice": "24100", "openPrice": "-", "highPrice": "-", "lowPrice": "-", "closePrice": "-", "volume": 0, "name": "NIFTY14OCT2524100PE", "token": "42616", "SR Low -": "", "SR Low +": "", "SR PC -": "", "SR PC +": "", "SR High -": "", "SR High +": ""}, {"12.10.2025": "Put24250", "instrumentType": "Index Options", "expiryDate": "14-Oct-2025", "optionType": "Put", "strikePrice": "24250", "openPrice": "-", "highPrice": "-", "lowPrice": "-", "closePrice": "-", "volume": 0, "name": "NIFTY14OCT2524250PE", "token": "42628", "SR Low -": "", "SR Low +": "", "SR PC -": "", "SR PC +": "", "SR High -": "", "SR High +": ""}, {"12.10.2025": "Put24800", "instrumentType": "Index Options", "expiryDate": "14-Oct-2025", "optionType": "Put", "strikePrice": "24800", "openPrice": "-", "highPrice": "-", "lowPrice": "-", "closePrice": "-", "volume": 0, "name": "NIFTY14OCT2524800PE", "token": "42666", "SR Low -": "", "SR Low +": "", "SR PC -": "", "SR PC +": "", "SR High -": "", "SR High +": ""}, {"12.10.2025": "Call24900", "instrumentType": "Index Options", "expiryDate": "14-Oct-2025", "optionType": "Call", "strikePrice": "24900", "openPrice": "-", "highPrice": "-", "lowPrice": "-", "closePrice": "-", "volume": 0, "name": "NIFTY14OCT2524900CE", "token": "42669", "SR Low -": "", "SR Low +": "", "SR PC -": "", "SR PC +": "", "SR High -": "", "SR High +": ""}, {"12.10.2025": "Put24950", "instrumentType": "Index Options", "expiryDate": "14-Oct-2025", "optionType": "Put", "strikePrice": "24950", "openPrice": "-", "highPrice": "-", "lowPrice": "-", "closePrice": "-", "volume": 0, "name": "NIFTY14OCT2524950PE", "token": "42672", "SR Low -": "", "SR Low +": "", "SR PC -": "", "SR PC +": "", "SR High -": "", "SR High +": ""}, {"12.10.2025": "Put25700", "instrumentType": "Index Options", "expiryDate": "14-Oct-2025", "optionType": "Put", "strikePrice": "25700", "openPrice": "-", "highPrice": "-", "lowPrice": "-", "closePrice": "-", "volume": 0, "name": "NIFTY14OCT2525700PE", "token": "42718", "SR Low -": "", "SR Low +": "", "SR PC -": "", "SR PC +": "", "SR High -": "", "SR High +": ""}, {"12.10.2025": "Call26050", "instrumentType": "Index Options", "expiryDate": "14-Oct-2025", "optionType": "Call", "strikePrice": "26050", "openPrice": "-", "highPrice": "-", "lowPrice": "-", "closePrice": "-", "volume": 0, "name": "NIFTY14OCT2526050CE", "token": "42735", "SR Low -": "", "SR Low +": "", "SR PC -": "", "SR PC +": "", "SR High -": "", "SR High +": ""}, {"12.10.2025": "Put26300", "instrumentType": "Index Options", "expiryDate": "14-Oct-2025", "optionType": "Put", "strikePrice": "26300", "openPrice": "-", "highPrice": "-", "lowPrice": "-", "closePrice": "-", "volume": 0, "name": "NIFTY14OCT2526300PE", "token": "42752", "SR Low -": "", "SR Low +": "", "SR PC -": "", "SR PC +": "", "SR High -": "", "SR High +": ""}, {"12.10.2025": "Put26350", "instrumentType": "Index Options", "expiryDate": "14-Oct-2025", "optionType": "Put", "strikePrice": "26350", "openPrice": "-", "highPrice": "-", "lowPrice": "-", "closePrice": "-", "volume": 0, "name": "NIFTY14OCT2526350PE", "token": "42754", "SR Low -": "", "SR Low +": "", "SR PC -": "", "SR PC +": "", "SR High -": "", "SR High +": ""}, {"12.10.2025": "Put26500", "instrumentType": "Index Options", "expiryDate": "14-Oct-2025", "optionType": "Put", "strikePrice": "26500", "openPrice": "-", "highPrice": "-", "lowPrice": "-", "closePrice": "-", "volume": 0, "name": "NIFTY14OCT2526500PE", "token": "42760", "SR Low -": "", "SR Low +": "", "SR PC -": "", "SR PC +": "", "SR High -": "", "SR High +": ""}, {"12.10.2025": "Put26750", "instrumentType": "Index Options", "expiryDate": "14-Oct-2025", "optionType": "Put", "strikePrice": "26750", "openPrice": "-", "highPrice": "-", "lowPrice": "-", "closePrice": "-", "volume": 0, "name": "NIFTY14OCT2526750PE", "token": "42772", "SR Low -": "", "SR Low +": "", "SR PC -": "", "SR PC +": "", "SR High -": "", "SR High +": ""}, {"12.10.2025": "Call23000", "instrumentType": "Index Options", "expiryDate": "14-Oct-2025", "optionType": "Call", "strikePrice": "23000", "openPrice": "-", "highPrice": "-", "lowPrice": "-", "closePrice": "-", "volume": 0, "name": "NIFTY14OCT2523000CE", "token": "42541", "SR Low -": "", "SR Low +": "", "SR PC -": "", "SR PC +": "", "SR High -": "", "SR High +": ""}, {"12.10.2025": "Put23050", "instrumentType": "Index Options", "expiryDate": "14-Oct-2025", "optionType": "Put", "strikePrice": "23050", "openPrice": "-", "highPrice": "-", "lowPrice": "-", "closePrice": "-", "volume": 0, "name": "NIFTY14OCT2523050PE", "token": "42544", "SR Low -": "", "SR Low +": "", "SR PC -": "", "SR PC +": "", "SR High -": "", "SR High +": ""}, {"12.10.2025": "Call23250", "instrumentType": "Index Options", "expiryDate": "14-Oct-2025", "optionType": "Call", "strikePrice": "23250", "openPrice": "-", "highPrice": "-", "lowPrice": "-", "closePrice": "-", "volume": 0, "name": "NIFTY14OCT2523250CE", "token": "42558", "SR Low -": "", "SR Low +": "", "SR PC -": "", "SR PC +": "", "SR High -": "", "SR High +": ""}, {"12.10.2025": "Call23450", "instrumentType": "Index Options", "expiryDate": "14-Oct-2025", "optionType": "Call", "strikePrice": "23450", "openPrice": "-", "highPrice": "-", "lowPrice": "-", "closePrice": "-", "volume": 0, "name": "NIFTY14OCT2523450CE", "token": "42583", "SR Low -": "", "SR Low +": "", "SR PC -": "", "SR PC +": "", "SR High -": "", "SR High +": ""}, {"12.10.2025": "Call23700", "instrumentType": "Index Options", "expiryDate": "14-Oct-2025", "optionType": "Call", "strikePrice": "23700", "openPrice": "-", "highPrice": "-", "lowPrice": "-", "closePrice": "-", "volume": 0, "name": "NIFTY14OCT2523700CE", "token": "42595", "SR Low -": "", "SR Low +": "", "SR PC -": "", "SR PC +": "", "SR High -": "", "SR High +": ""}, {"12.10.2025": "Put24450", "instrumentType": "Index Options", "expiryDate": "14-Oct-2025", "optionType": "Put", "strikePrice": "24450", "openPrice": "-", "highPrice": "-", "lowPrice": "-", "closePrice": "-", "volume": 0, "name": "NIFTY14OCT2524450PE", "token": "42644", "SR Low -": "", "SR Low +": "", "SR PC -": "", "SR PC +": "", "SR High -": "", "SR High +": ""}, {"12.10.2025": "Put24650", "instrumentType": "Index Options", "expiryDate": "14-Oct-2025", "optionType": "Put", "strikePrice": "24650", "openPrice": "-", "highPrice": "-", "lowPrice": "-", "closePrice": "-", "volume": 0, "name": "NIFTY14OCT2524650PE", "token": "42652", "SR Low -": "", "SR Low +": "", "SR PC -": "", "SR PC +": "", "SR High -": "", "SR High +": ""}, {"12.10.2025": "Call25250", "instrumentType": "Index Options", "expiryDate": "14-Oct-2025", "optionType": "Call", "strikePrice": "25250", "openPrice": "-", "highPrice": "-", "lowPrice": "-", "closePrice": "-", "volume": 0, "name": "NIFTY14OCT2525250CE", "token": "42691", "SR Low -": "", "SR Low +": "", "SR PC -": "", "SR PC +": "", "SR High -": "", "SR High +": ""}, {"12.10.2025": "Call25300", "instrumentType": "Index Options", "expiryDate": "14-Oct-2025", "optionType": "Call", "strikePrice": "25300", "openPrice": "-", "highPrice": "-", "lowPrice": "-", "closePrice": "-", "volume": 0, "name": "NIFTY14OCT2525300CE", "token": "42693", "SR Low -": "", "SR Low +": "", "SR PC -": "", "SR PC +": "", "SR High -": "", "SR High +": ""}, {"12.10.2025": "Call25400", "instrumentType": "Index Options", "expiryDate": "14-Oct-2025", "optionType": "Call", "strikePrice": "25400", "openPrice": "-", "highPrice": "-", "lowPrice": "-", "closePrice": "-", "volume": 0, "name": "NIFTY14OCT2525400CE", "token": "42703", "SR Low -": "", "SR Low +": "", "SR PC -": "", "SR PC +": "", "SR High -": "", "SR High +": ""}, {"12.10.2025": "Put25400", "instrumentType": "Index Options", "expiryDate": "14-Oct-2025", "optionType": "Put", "strikePrice": "25400", "openPrice": "-", "highPrice": "-", "lowPrice": "-", "closePrice": "-", "volume": 0, "name": "NIFTY14OCT2525400PE", "token": "42704", "SR Low -": "", "SR Low +": "", "SR PC -": "", "SR PC +": "", "SR High -": "", "SR High +": ""}, {"12.10.2025": "Put25500", "instrumentType": "Index Options", "expiryDate": "14-Oct-2025", "optionType": "Put", "strikePrice": "25500", "openPrice": "-", "highPrice": "-", "lowPrice": "-", "closePrice": "-", "volume": 0, "name": "NIFTY14OCT2525500PE", "token": "42709", "SR Low -": "", "SR Low +": "", "SR PC -": "", "SR PC +": "", "SR High -": "", "SR High +": ""}, {"12.10.2025": "Put25550", "instrumentType": "Index Options", "expiryDate": "14-Oct-2025", "optionType": "Put", "strikePrice": "25550", "openPrice": "-", "highPrice": "-", "lowPrice": "-", "closePrice": "-", "volume": 0, "name": "NIFTY14OCT2525550PE", "token": "42712", "SR Low -": "", "SR Low +": "", "SR PC -": "", "SR PC +": "", "SR High -": "", "SR High +": ""}, {"12.10.2025": "Call25850", "instrumentType": "Index Options", "expiryDate": "14-Oct-2025", "optionType": "Call", "strikePrice": "25850", "openPrice": "-", "highPrice": "-", "lowPrice": "-", "closePrice": "-", "volume": 0, "name": "NIFTY14OCT2525850CE", "token": "42723", "SR Low -": "", "SR Low +": "", "SR PC -": "", "SR PC +": "", "SR High -": "", "SR High +": ""}, {"12.10.2025": "Put25850", "instrumentType": "Index Options", "expiryDate": "14-Oct-2025", "optionType": "Put", "strikePrice": "25850", "openPrice": "-", "highPrice": "-", "lowPrice": "-", "closePrice": "-", "volume": 0, "name": "NIFTY14OCT2525850PE", "token": "42724", "SR Low -": "", "SR Low +": "", "SR PC -": "", "SR PC +": "", "SR High -": "", "SR High +": ""}, {"12.10.2025": "Call25950", "instrumentType": "Index Options", "expiryDate": "14-Oct-2025", "optionType": "Call", "strikePrice": "25950", "openPrice": "-", "highPrice": "-", "lowPrice": "-", "closePrice": "-", "volume": 0, "name": "NIFTY14OCT2525950CE", "token": "42731", "SR Low -": "", "SR Low +": "", "SR PC -": "", "SR PC +": "", "SR High -": "", "SR High +": ""}, {"12.10.2025": "Put26200", "instrumentType": "Index Options", "expiryDate": "14-Oct-2025", "optionType": "Put", "strikePrice": "26200", "openPrice": "-", "highPrice": "-", "lowPrice": "-", "closePrice": "-", "volume": 0, "name": "NIFTY14OCT2526200PE", "token": "42744", "SR Low -": "", "SR Low +": "", "SR PC -": "", "SR PC +": "", "SR High -": "", "SR High +": ""}, {"12.10.2025": "Call26750", "instrumentType": "Index Options", "expiryDate": "14-Oct-2025", "optionType": "Call", "strikePrice": "26750", "openPrice": "-", "highPrice": "-", "lowPrice": "-", "closePrice": "-", "volume": 0, "name": "NIFTY14OCT2526750CE", "token": "42771", "SR Low -": "", "SR Low +": "", "SR PC -": "", "SR PC +": "", "SR High -": "", "SR High +": ""}, {"12.10.2025": "Call26950", "instrumentType": "Index Options", "expiryDate": "14-Oct-2025", "optionType": "Call", "strikePrice": "26950", "openPrice": "-", "highPrice": "-", "lowPrice": "-", "closePrice": "-", "volume": 0, "name": "NIFTY14OCT2526950CE", "token": "42781", "SR Low -": "", "SR Low +": "", "SR PC -": "", "SR PC +": "", "SR High -": "", "SR High +": ""}, {"12.10.2025": "Put27000", "instrumentType": "Index Options", "expiryDate": "14-Oct-2025", "optionType": "Put", "strikePrice": "27000", "openPrice": "-", "highPrice": "-", "lowPrice": "-", "closePrice": "-", "volume": 0, "name": "NIFTY14OCT2527000PE", "token": "42784", "SR Low -": "", "SR Low +": "", "SR PC -": "", "SR PC +": "", "SR High -": "", "SR High +": ""}, {"12.10.2025": "Call27100", "instrumentType": "Index Options", "expiryDate": "14-Oct-2025", "optionType": "Call", "strikePrice": "27100", "openPrice": "-", "highPrice": "-", "lowPrice": "-", "closePrice": "-", "volume": 0, "name": "NIFTY14OCT2527100CE", "token": "42787", "SR Low -": "", "SR Low +": "", "SR PC -": "", "SR PC +": "", "SR High -": "", "SR High +": ""}, {"12.10.2025": "Call22850", "instrumentType": "Index Options", "expiryDate": "14-Oct-2025", "optionType": "Call", "strikePrice": "22850", "openPrice": "-", "highPrice": "-", "lowPrice": "-", "closePrice": "-", "volume": 0, "name": "NIFTY14OCT2522850CE", "token": "42535", "SR Low -": "", "SR Low +": "", "SR PC -": "", "SR PC +": "", "SR High -": "", "SR High +": ""}, {"12.10.2025": "Call22950", "instrumentType": "Index Options", "expiryDate": "14-Oct-2025", "optionType": "Call", "strikePrice": "22950", "openPrice": "-", "highPrice": "-", "lowPrice": "-", "closePrice": "-", "volume": 0, "name": "NIFTY14OCT2522950CE", "token": "42539", "SR Low -": "", "SR Low +": "", "SR PC -": "", "SR PC +": "", "SR High -": "", "SR High +": ""}, {"12.10.2025": "Call23150", "instrumentType": "Index Options", "expiryDate": "14-Oct-2025", "optionType": "Call", "strikePrice": "23150", "openPrice": "-", "highPrice": "-", "lowPrice": "-", "closePrice": "-", "volume": 0, "name": "NIFTY14OCT2523150CE", "token": "42550", "SR Low -": "", "SR Low +": "", "SR PC -": "", "SR PC +": "", "SR High -": "", "SR High +": ""}, {"12.10.2025": "Call23350", "instrumentType": "Index Options", "expiryDate": "14-Oct-2025", "optionType": "Call", "strikePrice": "23350", "openPrice": "-", "highPrice": "-", "lowPrice": "-", "closePrice": "-", "volume": 0, "name": "NIFTY14OCT2523350CE", "token": "42575", "SR Low -": "", "SR Low +": "", "SR PC -": "", "SR PC +": "", "SR High -": "", "SR High +": ""}, {"12.10.2025": "Call23400", "instrumentType": "Index Options", "expiryDate": "14-Oct-2025", "optionType": "Call", "strikePrice": "23400", "openPrice": "-", "highPrice": "-", "lowPrice": "-", "closePrice": "-", "volume": 0, "name": "NIFTY14OCT2523400CE", "token": "42577", "SR Low -": "", "SR Low +": "", "SR PC -": "", "SR PC +": "", "SR High -": "", "SR High +": ""}, {"12.10.2025": "Call23800", "instrumentType": "Index Options", "expiryDate": "14-Oct-2025", "optionType": "Call", "strikePrice": "23800", "openPrice": "-", "highPrice": "-", "lowPrice": "-", "closePrice": "-", "volume": 0, "name": "NIFTY14OCT2523800CE", "token": "42601", "SR Low -": "", "SR Low +": "", "SR PC -": "", "SR PC +": "", "SR High -": "", "SR High +": ""}, {"12.10.2025": "Put23900", "instrumentType": "Index Options", "expiryDate": "14-Oct-2025", "optionType": "Put", "strikePrice": "23900", "openPrice": "-", "highPrice": "-", "lowPrice": "-", "closePrice": "-", "volume": 0, "name": "NIFTY14OCT2523900PE", "token": "42606", "SR Low -": "", "SR Low +": "", "SR PC -": "", "SR PC +": "", "SR High -": "", "SR High +": ""}, {"12.10.2025": "Call24000", "instrumentType": "Index Options", "expiryDate": "14-Oct-2025", "optionType": "Call", "strikePrice": "24000", "openPrice": "-", "highPrice": "-", "lowPrice": "-", "closePrice": "-", "volume": 0, "name": "NIFTY14OCT2524000CE", "token": "42609", "SR Low -": "", "SR Low +": "", "SR PC -": "", "SR PC +": "", "SR High -": "", "SR High +": ""}, {"12.10.2025": "Put24850", "instrumentType": "Index Options", "expiryDate": "14-Oct-2025", "optionType": "Put", "strikePrice": "24850", "openPrice": "-", "highPrice": "-", "lowPrice": "-", "closePrice": "-", "volume": 0, "name": "NIFTY14OCT2524850PE", "token": "42668", "SR Low -": "", "SR Low +": "", "SR PC -": "", "SR PC +": "", "SR High -": "", "SR High +": ""}, {"12.10.2025": "Put25050", "instrumentType": "Index Options", "expiryDate": "14-Oct-2025", "optionType": "Put", "strikePrice": "25050", "openPrice": "-", "highPrice": "-", "lowPrice": "-", "closePrice": "-", "volume": 0, "name": "NIFTY14OCT2525050PE", "token": "42678", "SR Low -": "", "SR Low +": "", "SR PC -": "", "SR PC +": "", "SR High -": "", "SR High +": ""}, {"12.10.2025": "Call25100", "instrumentType": "Index Options", "expiryDate": "14-Oct-2025", "optionType": "Call", "strikePrice": "25100", "openPrice": "-", "highPrice": "-", "lowPrice": "-", "closePrice": "-", "volume": 0, "name": "NIFTY14OCT2525100CE", "token": "42679", "SR Low -": "", "SR Low +": "", "SR PC -": "", "SR PC +": "", "SR High -": "", "SR High +": ""}, {"12.10.2025": "Put25150", "instrumentType": "Index Options", "expiryDate": "14-Oct-2025", "optionType": "Put", "strikePrice": "25150", "openPrice": "-", "highPrice": "-", "lowPrice": "-", "closePrice": "-", "volume": 0, "name": "NIFTY14OCT2525150PE", "token": "42686", "SR Low -": "", "SR Low +": "", "SR PC -": "", "SR PC +": "", "SR High -": "", "SR High +": ""}, {"12.10.2025": "Call25200", "instrumentType": "Index Options", "expiryDate": "14-Oct-2025", "optionType": "Call", "strikePrice": "25200", "openPrice": "-", "highPrice": "-", "lowPrice": "-", "closePrice": "-", "volume": 0, "name": "NIFTY14OCT2525200CE", "token": "42687", "SR Low -": "", "SR Low +": "", "SR PC -": "", "SR PC +": "", "SR High -": "", "SR High +": ""}, {"12.10.2025": "Call25600", "instrumentType": "Index Options", "expiryDate": "14-Oct-2025", "optionType": "Call", "strikePrice": "25600", "openPrice": "-", "highPrice": "-", "lowPrice": "-", "closePrice": "-", "volume": 0, "name": "NIFTY14OCT2525600CE", "token": "42713", "SR Low -": "", "SR Low +": "", "SR PC -": "", "SR PC +": "", "SR High -": "", "SR High +": ""}, {"12.10.2025": "Put25750", "instrumentType": "Index Options", "expiryDate": "14-Oct-2025", "optionType": "Put", "strikePrice": "25750", "openPrice": "-", "highPrice": "-", "lowPrice": "-", "closePrice": "-", "volume": 0, "name": "NIFTY14OCT2525750PE", "token": "42720", "SR Low -": "", "SR Low +": "", "SR PC -": "", "SR PC +": "", "SR High -": "", "SR High +": ""}, {"12.10.2025": "Call25800", "instrumentType": "Index Options", "expiryDate": "14-Oct-2025", "optionType": "Call", "strikePrice": "25800", "openPrice": "-", "highPrice": "-", "lowPrice": "-", "closePrice": "-", "volume": 0, "name": "NIFTY14OCT2525800CE", "token": "42721", "SR Low -": "", "SR Low +": "", "SR PC -": "", "SR PC +": "", "SR High -": "", "SR High +": ""}, {"12.10.2025": "Put25900", "instrumentType": "Index Options", "expiryDate": "14-Oct-2025", "optionType": "Put", "strikePrice": "25900", "openPrice": "-", "highPrice": "-", "lowPrice": "-", "closePrice": "-", "volume": 0, "name": "NIFTY14OCT2525900PE", "token": "42730", "SR Low -": "", "SR Low +": "", "SR PC -": "", "SR PC +": "", "SR High -": "", "SR High +": ""}, {"12.10.2025": "Put26050", "instrumentType": "Index Options", "expiryDate": "14-Oct-2025", "optionType": "Put", "strikePrice": "26050", "openPrice": "-", "highPrice": "-", "lowPrice": "-", "closePrice": "-", "volume": 0, "name": "NIFTY14OCT2526050PE", "token": "42738", "SR Low -": "", "SR Low +": "", "SR PC -": "", "SR PC +": "", "SR High -": "", "SR High +": ""}, {"12.10.2025": "Call26250", "instrumentType": "Index Options", "expiryDate": "14-Oct-2025", "optionType": "Call", "strikePrice": "26250", "openPrice": "-", "highPrice": "-", "lowPrice": "-", "closePrice": "-", "volume": 0, "name": "NIFTY14OCT2526250CE", "token": "42745", "SR Low -": "", "SR Low +": "", "SR PC -": "", "SR PC +": "", "SR High -": "", "SR High +": ""}, {"12.10.2025": "Put26600", "instrumentType": "Index Options", "expiryDate": "14-Oct-2025", "optionType": "Put", "strikePrice": "26600", "openPrice": "-", "highPrice": "-", "lowPrice": "-", "closePrice": "-", "volume": 0, "name": "NIFTY14OCT2526600PE", "token": "42766", "SR Low -": "", "SR Low +": "", "SR PC -": "", "SR PC +": "", "SR High -": "", "SR High +": ""}, {"12.10.2025": "Call26700", "instrumentType": "Index Options", "expiryDate": "14-Oct-2025", "optionType": "Call", "strikePrice": "26700", "openPrice": "-", "highPrice": "-", "lowPrice": "-", "closePrice": "-", "volume": 0, "name": "NIFTY14OCT2526700CE", "token": "42769", "SR Low -": "", "SR Low +": "", "SR PC -": "", "SR PC +": "", "SR High -": "", "SR High +": ""}, {"12.10.2025": "Put26800", "instrumentType": "Index Options", "expiryDate": "14-Oct-2025", "optionType": "Put", "strikePrice": "26800", "openPrice": "-", "highPrice": "-", "lowPrice": "-", "closePrice": "-", "volume": 0, "name": "NIFTY14OCT2526800PE", "token": "42774", "SR Low -": "", "SR Low +": "", "SR PC -": "", "SR PC +": "", "SR High -": "", "SR High +": ""}, {"12.10.2025": "Put26900", "instrumentType": "Index Options", "expiryDate": "14-Oct-2025", "optionType": "Put", "strikePrice": "26900", "openPrice": "-", "highPrice": "-", "lowPrice": "-", "closePrice": "-", "volume": 0, "name": "NIFTY14OCT2526900PE", "token": "42780", "SR Low -": "", "SR Low +": "", "SR PC -": "", "SR PC +": "", "SR High -": "", "SR High +": ""}, {"12.10.2025": "Put23300", "instrumentType": "Index Options", "expiryDate": "14-Oct-2025", "optionType": "Put", "strikePrice": "23300", "openPrice": "-", "highPrice": "-", "lowPrice": "-", "closePrice": "-", "volume": 0, "name": "NIFTY14OCT2523300PE", "token": "42574", "SR Low -": "", "SR Low +": "", "SR PC -": "", "SR PC +": "", "SR High -": "", "SR High +": ""}, {"12.10.2025": "Put23450", "instrumentType": "Index Options", "expiryDate": "14-Oct-2025", "optionType": "Put", "strikePrice": "23450", "openPrice": "-", "highPrice": "-", "lowPrice": "-", "closePrice": "-", "volume": 0, "name": "NIFTY14OCT2523450PE", "token": "42584", "SR Low -": "", "SR Low +": "", "SR PC -": "", "SR PC +": "", "SR High -": "", "SR High +": ""}, {"12.10.2025": "Put23650", "instrumentType": "Index Options", "expiryDate": "14-Oct-2025", "optionType": "Put", "strikePrice": "23650", "openPrice": "-", "highPrice": "-", "lowPrice": "-", "closePrice": "-", "volume": 0, "name": "NIFTY14OCT2523650PE", "token": "42594", "SR Low -": "", "SR Low +": "", "SR PC -": "", "SR PC +": "", "SR High -": "", "SR High +": ""}, {"12.10.2025": "Call24100", "instrumentType": "Index Options", "expiryDate": "14-Oct-2025", "optionType": "Call", "strikePrice": "24100", "openPrice": "-", "highPrice": "-", "lowPrice": "-", "closePrice": "-", "volume": 0, "name": "NIFTY14OCT2524100CE", "token": "42615", "SR Low -": "", "SR Low +": "", "SR PC -": "", "SR PC +": "", "SR High -": "", "SR High +": ""}, {"12.10.2025": "Put24150", "instrumentType": "Index Options", "expiryDate": "14-Oct-2025", "optionType": "Put", "strikePrice": "24150", "openPrice": "-", "highPrice": "-", "lowPrice": "-", "closePrice": "-", "volume": 0, "name": "NIFTY14OCT2524150PE", "token": "42620", "SR Low -": "", "SR Low +": "", "SR PC -": "", "SR PC +": "", "SR High -": "", "SR High +": ""}, {"12.10.2025": "Put24300", "instrumentType": "Index Options", "expiryDate": "14-Oct-2025", "optionType": "Put", "strikePrice": "24300", "openPrice": "-", "highPrice": "-", "lowPrice": "-", "closePrice": "-", "volume": 0, "name": "NIFTY14OCT2524300PE", "token": "42630", "SR Low -": "", "SR Low +": "", "SR PC -": "", "SR PC +": "", "SR High -": "", "SR High +": ""}, {"12.10.2025": "Call24650", "instrumentType": "Index Options", "expiryDate": "14-Oct-2025", "optionType": "Call", "strikePrice": "24650", "openPrice": "-", "highPrice": "-", "lowPrice": "-", "closePrice": "-", "volume": 0, "name": "NIFTY14OCT2524650CE", "token": "42651", "SR Low -": "", "SR Low +": "", "SR PC -": "", "SR PC +": "", "SR High -": "", "SR High +": ""}, {"12.10.2025": "Call24700", "instrumentType": "Index Options", "expiryDate": "14-Oct-2025", "optionType": "Call", "strikePrice": "24700", "openPrice": "-", "highPrice": "-", "lowPrice": "-", "closePrice": "-", "volume": 0, "name": "NIFTY14OCT2524700CE", "token": "42653", "SR Low -": "", "SR Low +": "", "SR PC -": "", "SR PC +": "", "SR High -": "", "SR High +": ""}, {"12.10.2025": "Put24750", "instrumentType": "Index Options", "expiryDate": "14-Oct-2025", "optionType": "Put", "strikePrice": "24750", "openPrice": "-", "highPrice": "-", "lowPrice": "-", "closePrice": "-", "volume": 0, "name": "NIFTY14OCT2524750PE", "token": "42660", "SR Low -": "", "SR Low +": "", "SR PC -": "", "SR PC +": "", "SR High -": "", "SR High +": ""}, {"12.10.2025": "Call24850", "instrumentType": "Index Options", "expiryDate": "14-Oct-2025", "optionType": "Call", "strikePrice": "24850", "openPrice": "-", "highPrice": "-", "lowPrice": "-", "closePrice": "-", "volume": 0, "name": "NIFTY14OCT2524850CE", "token": "42667", "SR Low -": "", "SR Low +": "", "SR PC -": "", "SR PC +": "", "SR High -": "", "SR High +": ""}, {"12.10.2025": "Put25300", "instrumentType": "Index Options", "expiryDate": "14-Oct-2025", "optionType": "Put", "strikePrice": "25300", "openPrice": "-", "highPrice": "-", "lowPrice": "-", "closePrice": "-", "volume": 0, "name": "NIFTY14OCT2525300PE", "token": "42694", "SR Low -": "", "SR Low +": "", "SR PC -": "", "SR PC +": "", "SR High -": "", "SR High +": ""}, {"12.10.2025": "Call25900", "instrumentType": "Index Options", "expiryDate": "14-Oct-2025", "optionType": "Call", "strikePrice": "25900", "openPrice": "-", "highPrice": "-", "lowPrice": "-", "closePrice": "-", "volume": 0, "name": "NIFTY14OCT2525900CE", "token": "42725", "SR Low -": "", "SR Low +": "", "SR PC -": "", "SR PC +": "", "SR High -": "", "SR High +": ""}, {"12.10.2025": "Call26100", "instrumentType": "Index Options", "expiryDate": "14-Oct-2025", "optionType": "Call", "strikePrice": "26100", "openPrice": "-", "highPrice": "-", "lowPrice": "-", "closePrice": "-", "volume": 0, "name": "NIFTY14OCT2526100CE", "token": "42739", "SR Low -": "", "SR Low +": "", "SR PC -": "", "SR PC +": "", "SR High -": "", "SR High +": ""}, {"12.10.2025": "Call26350", "instrumentType": "Index Options", "expiryDate": "14-Oct-2025", "optionType": "Call", "strikePrice": "26350", "openPrice": "-", "highPrice": "-", "lowPrice": "-", "closePrice": "-", "volume": 0, "name": "NIFTY14OCT2526350CE", "token": "42753", "SR Low -": "", "SR Low +": "", "SR PC -": "", "SR PC +": "", "SR High -": "", "SR High +": ""}, {"12.10.2025": "Call26650", "instrumentType": "Index Options", "expiryDate": "14-Oct-2025", "optionType": "Call", "strikePrice": "26650", "openPrice": "-", "highPrice": "-", "lowPrice": "-", "closePrice": "-", "volume": 0, "name": "NIFTY14OCT2526650CE", "token": "42767", "SR Low -": "", "SR Low +": "", "SR PC -": "", "SR PC +": "", "SR High -": "", "SR High +": ""}, {"12.10.2025": "Call27050", "instrumentType": "Index Options", "expiryDate": "14-Oct-2025", "optionType": "Call", "strikePrice": "27050", "openPrice": "-", "highPrice": "-", "lowPrice": "-", "closePrice": "-", "volume": 0, "name": "NIFTY14OCT2527050CE", "token": "42785", "SR Low -": "", "SR Low +": "", "SR PC -": "", "SR PC +": "", "SR High -": "", "SR High +": ""}, {"12.10.2025": "Put27050", "instrumentType": "Index Options", "expiryDate": "14-Oct-2025", "optionType": "Put", "strikePrice": "27050", "openPrice": "-", "highPrice": "-", "lowPrice": "-", "closePrice": "-", "volume": 0, "name": "NIFTY14OCT2527050PE", "token": "42786", "SR Low -": "", "SR Low +": "", "SR PC -": "", "SR PC +": "", "SR High -": "", "SR High +": ""}]