[{"06.02.2026": "Put25600", "instrumentType": "Index Options", "expiryDate": "10-Feb-2026", "optionType": "Put", "strikePrice": "25600", "openPrice": 111.0, "highPrice": 170.1, "lowPrice": 64.75, "closePrice": 70.5, "volume": 8349834, "name": "NIFTY10FEB2625600PE", "token": "42527", "SR Low -": 25535.25, "SR Low +": 25664.75, "SR PC -": 25529.5, "SR PC +": 25670.5, "SR High -": 25429.9, "SR High +": 25770.1}, {"06.02.2026": "Put25500", "instrumentType": "Index Options", "expiryDate": "10-Feb-2026", "optionType": "Put", "strikePrice": "25500", "openPrice": 76.5, "highPrice": 113.4, "lowPrice": 39.3, "closePrice": 43.7, "volume": 8250130, "name": "NIFTY10FEB2625500PE", "token": "42523", "SR Low -": 25460.7, "SR Low +": 25539.3, "SR PC -": 25456.3, "SR PC +": 25543.7, "SR High -": 25386.6, "SR High +": 25613.4}, {"06.02.2026": "Call25600", "instrumentType": "Index Options", "expiryDate": "10-Feb-2026", "optionType": "Call", "strikePrice": "25600", "openPrice": 149.6, "highPrice": 152.35, "lowPrice": 72.1, "closePrice": 145.9, "volume": 8087242, "name": "NIFTY10FEB2625600CE", "token": "42526", "SR Low -": 25527.9, "SR Low +": 25672.1, "SR PC -": 25454.1, "SR PC +": 25745.9, "SR High -": 25447.65, "SR High +": 25752.35}, {"06.02.2026": "Call25700", "instrumentType": "Index Options", "expiryDate": "10-Feb-2026", "optionType": "Call", "strikePrice": "25700", "openPrice": 77.0, "highPrice": 99.6, "lowPrice": 44.6, "closePrice": 90.4, "volume": 6183197, "name": "NIFTY10FEB2625700CE", "token": "42530", "SR Low -": 25655.4, "SR Low +": 25744.6, "SR PC -": 25609.6, "SR PC +": 25790.4, "SR High -": 25600.4, "SR High +": 25799.6}, {"06.02.2026": "Put25550", "instrumentType": "Index Options", "expiryDate": "10-Feb-2026", "optionType": "Put", "strikePrice": "25550", "openPrice": 103.8, "highPrice": 140.0, "lowPrice": 50.5, "closePrice": 55.65, "volume": 5959700, "name": "NIFTY10FEB2625550PE", "token": "42525", "SR Low -": 25499.5, "SR Low +": 25600.5, "SR PC -": 25494.35, "SR PC +": 25605.65, "SR High -": 25410.0, "SR High +": 25690.0}, {"06.02.2026": "Call25650", "instrumentType": "Index Options", "expiryDate": "10-Feb-2026", "optionType": "Call", "strikePrice": "25650", "openPrice": 122.6, "highPrice": 122.6, "lowPrice": 56.65, "closePrice": 116.05, "volume": 5130300, "name": "NIFTY10FEB2625650CE", "token": "42528", "SR Low -": 25593.35, "SR Low +": 25706.65, "SR PC -": 25533.95, "SR PC +": 25766.05, "SR High -": 25527.4, "SR High +": 25772.6}, {"06.02.2026": "Call25800", "instrumentType": "Index Options", "expiryDate": "10-Feb-2026", "optionType": "Call", "strikePrice": "25800", "openPrice": 68.9, "highPrice": 68.9, "lowPrice": 27.8, "closePrice": 53.45, "volume": 4166601, "name": "NIFTY10FEB2625800CE", "token": "42536", "SR Low -": 25772.2, "SR Low +": 25827.8, "SR PC -": 25746.55, "SR PC +": 25853.45, "SR High -": 25731.1, "SR High +": 25868.9}, {"06.02.2026": "Put25400", "instrumentType": "Index Options", "expiryDate": "10-Feb-2026", "optionType": "Put", "strikePrice": "25400", "openPrice": 45.4, "highPrice": 70.05, "lowPrice": 25.0, "closePrice": 28.15, "volume": 3935162, "name": "NIFTY10FEB2625400PE", "token": "42519", "SR Low -": 25375.0, "SR Low +": 25425.0, "SR PC -": 25371.85, "SR PC +": 25428.15, "SR High -": 25329.95, "SR High +": 25470.05}, {"06.02.2026": "Call25550", "instrumentType": "Index Options", "expiryDate": "10-Feb-2026", "optionType": "Call", "strikePrice": "25550", "openPrice": 178.0, "highPrice": 187.95, "lowPrice": 91.0, "closePrice": 180.35, "volume": 3862779, "name": "NIFTY10FEB2625550CE", "token": "42524", "SR Low -": 25459.0, "SR Low +": 25641.0, "SR PC -": 25369.65, "SR PC +": 25730.35, "SR High -": 25362.05, "SR High +": 25737.95}, {"06.02.2026": "Call25500", "instrumentType": "Index Options", "expiryDate": "10-Feb-2026", "optionType": "Call", "strikePrice": "25500", "openPrice": 201.3, "highPrice": 226.0, "lowPrice": 114.0, "closePrice": 218.3, "volume": 3816419, "name": "NIFTY10FEB2625500CE", "token": "42522", "SR Low -": 25386.0, "SR Low +": 25614.0, "SR PC -": 25281.7, "SR PC +": 25718.3, "SR High -": 25274.0, "SR High +": 25726.0}, {"06.02.2026": "Put25650", "instrumentType": "Index Options", "expiryDate": "10-Feb-2026", "optionType": "Put", "strikePrice": "25650", "openPrice": 145.0, "highPrice": 205.0, "lowPrice": 83.7, "closePrice": 90.4, "volume": 3093902, "name": "NIFTY10FEB2625650PE", "token": "42529", "SR Low -": 25566.3, "SR Low +": 25733.7, "SR PC -": 25559.6, "SR PC +": 25740.4, "SR High -": 25445.0, "SR High +": 25855.0}, {"06.02.2026": "Put25450", "instrumentType": "Index Options", "expiryDate": "10-Feb-2026", "optionType": "Put", "strikePrice": "25450", "openPrice": 59.45, "highPrice": 89.95, "lowPrice": 30.95, "closePrice": 34.5, "volume": 3066902, "name": "NIFTY10FEB2625450PE", "token": "42521", "SR Low -": 25419.05, "SR Low +": 25480.95, "SR PC -": 25415.5, "SR PC +": 25484.5, "SR High -": 25360.05, "SR High +": 25539.95}, {"06.02.2026": "Call25750", "instrumentType": "Index Options", "expiryDate": "10-Feb-2026", "optionType": "Call", "strikePrice": "25750", "openPrice": 82.0, "highPrice": 82.0, "lowPrice": 35.2, "closePrice": 69.6, "volume": 2919754, "name": "NIFTY10FEB2625750CE", "token": "42532", "SR Low -": 25714.8, "SR Low +": 25785.2, "SR PC -": 25680.4, "SR PC +": 25819.6, "SR High -": 25668.0, "SR High +": 25832.0}, {"06.02.2026": "Put25700", "instrumentType": "Index Options", "expiryDate": "10-Feb-2026", "optionType": "Put", "strikePrice": "25700", "openPrice": 172.65, "highPrice": 243.0, "lowPrice": 107.25, "closePrice": 114.7, "volume": 2758595, "name": "NIFTY10FEB2625700PE", "token": "42531", "SR Low -": 25592.75, "SR Low +": 25807.25, "SR PC -": 25585.3, "SR PC +": 25814.7, "SR High -": 25457.0, "SR High +": 25943.0}, {"06.02.2026": "Call26000", "instrumentType": "Index Options", "expiryDate": "10-Feb-2026", "optionType": "Call", "strikePrice": "26000", "openPrice": 27.9, "highPrice": 27.9, "lowPrice": 12.0, "closePrice": 20.1, "volume": 2556522, "name": "NIFTY10FEB2626000CE", "token": "42546", "SR Low -": 25988.0, "SR Low +": 26012.0, "SR PC -": 25979.9, "SR PC +": 26020.1, "SR High -": 25972.1, "SR High +": 26027.9}, {"06.02.2026": "Call25900", "instrumentType": "Index Options", "expiryDate": "10-Feb-2026", "optionType": "Call", "strikePrice": "25900", "openPrice": 39.95, "highPrice": 39.95, "lowPrice": 17.35, "closePrice": 31.45, "volume": 2407447, "name": "NIFTY10FEB2625900CE", "token": "42540", "SR Low -": 25882.65, "SR Low +": 25917.35, "SR PC -": 25868.55, "SR PC +": 25931.45, "SR High -": 25860.05, "SR High +": 25939.95}, {"06.02.2026": "Put25300", "instrumentType": "Index Options", "expiryDate": "10-Feb-2026", "optionType": "Put", "strikePrice": "25300", "openPrice": 39.9, "highPrice": 43.0, "lowPrice": 17.5, "closePrice": 20.1, "volume": 2370948, "name": "NIFTY10FEB2625300PE", "token": "42513", "SR Low -": 25282.5, "SR Low +": 25317.5, "SR PC -": 25279.9, "SR PC +": 25320.1, "SR High -": 25257.0, "SR High +": 25343.0}, {"06.02.2026": "Call25850", "instrumentType": "Index Options", "expiryDate": "10-Feb-2026", "optionType": "Call", "strikePrice": "25850", "openPrice": 51.6, "highPrice": 51.6, "lowPrice": 21.75, "closePrice": 40.85, "volume": 1935410, "name": "NIFTY10FEB2625850CE", "token": "42538", "SR Low -": 25828.25, "SR Low +": 25871.75, "SR PC -": 25809.15, "SR PC +": 25890.85, "SR High -": 25798.4, "SR High +": 25901.6}, {"06.02.2026": "Put25350", "instrumentType": "Index Options", "expiryDate": "10-Feb-2026", "optionType": "Put", "strikePrice": "25350", "openPrice": 45.05, "highPrice": 54.95, "lowPrice": 20.6, "closePrice": 23.1, "volume": 1861534, "name": "NIFTY10FEB2625350PE", "token": "42517", "SR Low -": 25329.4, "SR Low +": 25370.6, "SR PC -": 25326.9, "SR PC +": 25373.1, "SR High -": 25295.05, "SR High +": 25404.95}, {"06.02.2026": "Put25200", "instrumentType": "Index Options", "expiryDate": "10-Feb-2026", "optionType": "Put", "strikePrice": "25200", "openPrice": 27.65, "highPrice": 27.65, "lowPrice": 13.3, "closePrice": 15.7, "volume": 1490306, "name": "NIFTY10FEB2625200PE", "token": "42509", "SR Low -": 25186.7, "SR Low +": 25213.3, "SR PC -": 25184.3, "SR PC +": 25215.7, "SR High -": 25172.35, "SR High +": 25227.65}, {"06.02.2026": "Call26500", "instrumentType": "Index Options", "expiryDate": "10-Feb-2026", "optionType": "Call", "strikePrice": "26500", "openPrice": 5.9, "highPrice": 7.45, "lowPrice": 4.0, "closePrice": 5.45, "volume": 1305865, "name": "NIFTY10FEB2626500CE", "token": "42570", "SR Low -": 26496.0, "SR Low +": 26504.0, "SR PC -": 26494.55, "SR PC +": 26505.45, "SR High -": 26492.55, "SR High +": 26507.45}, {"06.02.2026": "Put25000", "instrumentType": "Index Options", "expiryDate": "10-Feb-2026", "optionType": "Put", "strikePrice": "25000", "openPrice": 12.75, "highPrice": 15.6, "lowPrice": 8.7, "closePrice": 11.5, "volume": 1272928, "name": "NIFTY10FEB2625000PE", "token": "42501", "SR Low -": 24991.3, "SR Low +": 25008.7, "SR PC -": 24988.5, "SR PC +": 25011.5, "SR High -": 24984.4, "SR High +": 25015.6}, {"06.02.2026": "Call26100", "instrumentType": "Index Options", "expiryDate": "10-Feb-2026", "optionType": "Call", "strikePrice": "26100", "openPrice": 18.0, "highPrice": 19.4, "lowPrice": 8.8, "closePrice": 13.7, "volume": 1237348, "name": "NIFTY10FEB2626100CE", "token": "42552", "SR Low -": 26091.2, "SR Low +": 26108.8, "SR PC -": 26086.3, "SR PC +": 26113.7, "SR High -": 26080.6, "SR High +": 26119.4}, {"06.02.2026": "Call25950", "instrumentType": "Index Options", "expiryDate": "10-Feb-2026", "optionType": "Call", "strikePrice": "25950", "openPrice": 27.5, "highPrice": 31.4, "lowPrice": 14.2, "closePrice": 24.6, "volume": 1236034, "name": "NIFTY10FEB2625950CE", "token": "42544", "SR Low -": 25935.8, "SR Low +": 25964.2, "SR PC -": 25925.4, "SR PC +": 25974.6, "SR High -": 25918.6, "SR High +": 25981.4}, {"06.02.2026": "Put25250", "instrumentType": "Index Options", "expiryDate": "10-Feb-2026", "optionType": "Put", "strikePrice": "25250", "openPrice": 30.0, "highPrice": 33.8, "lowPrice": 15.15, "closePrice": 17.35, "volume": 1164587, "name": "NIFTY10FEB2625250PE", "token": "42511", "SR Low -": 25234.85, "SR Low +": 25265.15, "SR PC -": 25232.65, "SR PC +": 25267.35, "SR High -": 25216.2, "SR High +": 25283.8}, {"06.02.2026": "Call27000", "instrumentType": "Index Options", "expiryDate": "10-Feb-2026", "optionType": "Call", "strikePrice": "27000", "openPrice": 2.0, "highPrice": 2.85, "lowPrice": 1.6, "closePrice": 2.0, "volume": 1126796, "name": "NIFTY10FEB2627000CE", "token": "42600", "SR Low -": 26998.4, "SR Low +": 27001.6, "SR PC -": 26998.0, "SR PC +": 27002.0, "SR High -": 26997.15, "SR High +": 27002.85}, {"06.02.2026": "Call26200", "instrumentType": "Index Options", "expiryDate": "10-Feb-2026", "optionType": "Call", "strikePrice": "26200", "openPrice": 10.0, "highPrice": 12.7, "lowPrice": 7.05, "closePrice": 10.6, "volume": 959871, "name": "NIFTY10FEB2626200CE", "token": "42558", "SR Low -": 26192.95, "SR Low +": 26207.05, "SR PC -": 26189.4, "SR PC +": 26210.6, "SR High -": 26187.3, "SR High +": 26212.7}, {"06.02.2026": "Call26300", "instrumentType": "Index Options", "expiryDate": "10-Feb-2026", "optionType": "Call", "strikePrice": "26300", "openPrice": 9.0, "highPrice": 10.6, "lowPrice": 5.8, "closePrice": 8.45, "volume": 928017, "name": "NIFTY10FEB2626300CE", "token": "42562", "SR Low -": 26294.2, "SR Low +": 26305.8, "SR PC -": 26291.55, "SR PC +": 26308.45, "SR High -": 26289.4, "SR High +": 26310.6}, {"06.02.2026": "Put24500", "instrumentType": "Index Options", "expiryDate": "10-Feb-2026", "optionType": "Put", "strikePrice": "24500", "openPrice": 5.45, "highPrice": 7.1, "lowPrice": 4.15, "closePrice": 6.3, "volume": 915130, "name": "NIFTY10FEB2624500PE", "token": "42475", "SR Low -": 24495.85, "SR Low +": 24504.15, "SR PC -": 24493.7, "SR PC +": 24506.3, "SR High -": 24492.9, "SR High +": 24507.1}, {"06.02.2026": "Call26050", "instrumentType": "Index Options", "expiryDate": "10-Feb-2026", "optionType": "Call", "strikePrice": "26050", "openPrice": 24.4, "highPrice": 24.4, "lowPrice": 10.1, "closePrice": 16.2, "volume": 886529, "name": "NIFTY10FEB2626050CE", "token": "42548", "SR Low -": 26039.9, "SR Low +": 26060.1, "SR PC -": 26033.8, "SR PC +": 26066.2, "SR High -": 26025.6, "SR High +": 26074.4}, {"06.02.2026": "Put24000", "instrumentType": "Index Options", "expiryDate": "10-Feb-2026", "optionType": "Put", "strikePrice": "24000", "openPrice": 3.0, "highPrice": 4.25, "lowPrice": 2.2, "closePrice": 3.7, "volume": 884323, "name": "NIFTY10FEB2624000PE", "token": "42439", "SR Low -": 23997.8, "SR Low +": 24002.2, "SR PC -": 23996.3, "SR PC +": 24003.7, "SR High -": 23995.75, "SR High +": 24004.25}, {"06.02.2026": "Call26400", "instrumentType": "Index Options", "expiryDate": "10-Feb-2026", "optionType": "Call", "strikePrice": "26400", "openPrice": 8.85, "highPrice": 8.85, "lowPrice": 4.75, "closePrice": 6.7, "volume": 876005, "name": "NIFTY10FEB2626400CE", "token": "42566", "SR Low -": 26395.25, "SR Low +": 26404.75, "SR PC -": 26393.3, "SR PC +": 26406.7, "SR High -": 26391.15, "SR High +": 26408.85}, {"06.02.2026": "Call26600", "instrumentType": "Index Options", "expiryDate": "10-Feb-2026", "optionType": "Call", "strikePrice": "26600", "openPrice": 4.75, "highPrice": 6.65, "lowPrice": 3.25, "closePrice": 4.75, "volume": 849323, "name": "NIFTY10FEB2626600CE", "token": "42576", "SR Low -": 26596.75, "SR Low +": 26603.25, "SR PC -": 26595.25, "SR PC +": 26604.75, "SR High -": 26593.35, "SR High +": 26606.65}, {"06.02.2026": "Put25100", "instrumentType": "Index Options", "expiryDate": "10-Feb-2026", "optionType": "Put", "strikePrice": "25100", "openPrice": 25.0, "highPrice": 25.0, "lowPrice": 10.5, "closePrice": 13.3, "volume": 844072, "name": "NIFTY10FEB2625100PE", "token": "42505", "SR Low -": 25089.5, "SR Low +": 25110.5, "SR PC -": 25086.7, "SR PC +": 25113.3, "SR High -": 25075.0, "SR High +": 25125.0}, {"06.02.2026": "Put25800", "instrumentType": "Index Options", "expiryDate": "10-Feb-2026", "optionType": "Put", "strikePrice": "25800", "openPrice": 220.0, "highPrice": 325.3, "lowPrice": 168.05, "closePrice": 177.65, "volume": 761119, "name": "NIFTY10FEB2625800PE", "token": "42537", "SR Low -": 25631.95, "SR Low +": 25968.05, "SR PC -": 25622.35, "SR PC +": 25977.65, "SR High -": 25474.7, "SR High +": 26125.3}, {"06.02.2026": "Call26800", "instrumentType": "Index Options", "expiryDate": "10-Feb-2026", "optionType": "Call", "strikePrice": "26800", "openPrice": 3.9, "highPrice": 4.55, "lowPrice": 2.35, "closePrice": 3.15, "volume": 756601, "name": "NIFTY10FEB2626800CE", "token": "42584", "SR Low -": 26797.65, "SR Low +": 26802.35, "SR PC -": 26796.85, "SR PC +": 26803.15, "SR High -": 26795.45, "SR High +": 26804.55}, {"06.02.2026": "Call25400", "instrumentType": "Index Options", "expiryDate": "10-Feb-2026", "optionType": "Call", "strikePrice": "25400", "openPrice": 259.45, "highPrice": 311.9, "lowPrice": 171.15, "closePrice": 303.05, "volume": 671541, "name": "NIFTY10FEB2625400CE", "token": "42518", "SR Low -": 25228.85, "SR Low +": 25571.15, "SR PC -": 25096.95, "SR PC +": 25703.05, "SR High -": 25088.1, "SR High +": 25711.9}, {"06.02.2026": "Put25150", "instrumentType": "Index Options", "expiryDate": "10-Feb-2026", "optionType": "Put", "strikePrice": "25150", "openPrice": 25.0, "highPrice": 25.0, "lowPrice": 11.75, "closePrice": 14.35, "volume": 664092, "name": "NIFTY10FEB2625150PE", "token": "42507", "SR Low -": 25138.25, "SR Low +": 25161.75, "SR PC -": 25135.65, "SR PC +": 25164.35, "SR High -": 25125.0, "SR High +": 25175.0}, {"06.02.2026": "Call25450", "instrumentType": "Index Options", "expiryDate": "10-Feb-2026", "optionType": "Call", "strikePrice": "25450", "openPrice": 248.0, "highPrice": 267.9, "lowPrice": 140.65, "closePrice": 259.6, "volume": 663139, "name": "NIFTY10FEB2625450CE", "token": "42520", "SR Low -": 25309.35, "SR Low +": 25590.65, "SR PC -": 25190.4, "SR PC +": 25709.6, "SR High -": 25182.1, "SR High +": 25717.9}, {"06.02.2026": "Put25750", "instrumentType": "Index Options", "expiryDate": "10-Feb-2026", "optionType": "Put", "strikePrice": "25750", "openPrice": 198.45, "highPrice": 283.75, "lowPrice": 135.65, "closePrice": 144.05, "volume": 643148, "name": "NIFTY10FEB2625750PE", "token": "42535", "SR Low -": 25614.35, "SR Low +": 25885.65, "SR PC -": 25605.95, "SR PC +": 25894.05, "SR High -": 25466.25, "SR High +": 26033.75}, {"06.02.2026": "Call26150", "instrumentType": "Index Options", "expiryDate": "10-Feb-2026", "optionType": "Call", "strikePrice": "26150", "openPrice": 16.8, "highPrice": 16.8, "lowPrice": 7.8, "closePrice": 11.9, "volume": 614886, "name": "NIFTY10FEB2626150CE", "token": "42556", "SR Low -": 26142.2, "SR Low +": 26157.8, "SR PC -": 26138.1, "SR PC +": 26161.9, "SR High -": 26133.2, "SR High +": 26166.8}, {"06.02.2026": "Put24800", "instrumentType": "Index Options", "expiryDate": "10-Feb-2026", "optionType": "Put", "strikePrice": "24800", "openPrice": 11.0, "highPrice": 11.0, "lowPrice": 6.3, "closePrice": 9.1, "volume": 588001, "name": "NIFTY10FEB2624800PE", "token": "42491", "SR Low -": 24793.7, "SR Low +": 24806.3, "SR PC -": 24790.9, "SR PC +": 24809.1, "SR High -": 24789.0, "SR High +": 24811.0}, {"06.02.2026": "Call26700", "instrumentType": "Index Options", "expiryDate": "10-Feb-2026", "optionType": "Call", "strikePrice": "26700", "openPrice": 4.2, "highPrice": 5.4, "lowPrice": 2.75, "closePrice": 3.7, "volume": 587732, "name": "NIFTY10FEB2626700CE", "token": "42580", "SR Low -": 26697.25, "SR Low +": 26702.75, "SR PC -": 26696.3, "SR PC +": 26703.7, "SR High -": 26694.6, "SR High +": 26705.4}, {"06.02.2026": "Put24900", "instrumentType": "Index Options", "expiryDate": "10-Feb-2026", "optionType": "Put", "strikePrice": "24900", "openPrice": 9.5, "highPrice": 11.5, "lowPrice": 7.4, "closePrice": 10.1, "volume": 586542, "name": "NIFTY10FEB2624900PE", "token": "42497", "SR Low -": 24892.6, "SR Low +": 24907.4, "SR PC -": 24889.9, "SR PC +": 24910.1, "SR High -": 24888.5, "SR High +": 24911.5}, {"06.02.2026": "Call26250", "instrumentType": "Index Options", "expiryDate": "10-Feb-2026", "optionType": "Call", "strikePrice": "26250", "openPrice": 11.5, "highPrice": 11.6, "lowPrice": 6.4, "closePrice": 9.55, "volume": 541871, "name": "NIFTY10FEB2626250CE", "token": "42560", "SR Low -": 26243.6, "SR Low +": 26256.4, "SR PC -": 26240.45, "SR PC +": 26259.55, "SR High -": 26238.4, "SR High +": 26261.6}, {"06.02.2026": "Call26550", "instrumentType": "Index Options", "expiryDate": "10-Feb-2026", "optionType": "Call", "strikePrice": "26550", "openPrice": 6.4, "highPrice": 6.95, "lowPrice": 3.65, "closePrice": 5.0, "volume": 540478, "name": "NIFTY10FEB2626550CE", "token": "42572", "SR Low -": 26546.35, "SR Low +": 26553.65, "SR PC -": 26545.0, "SR PC +": 26555.0, "SR High -": 26543.05, "SR High +": 26556.95}, {"06.02.2026": "Call26350", "instrumentType": "Index Options", "expiryDate": "10-Feb-2026", "optionType": "Call", "strikePrice": "26350", "openPrice": 9.4, "highPrice": 10.3, "lowPrice": 5.25, "closePrice": 7.65, "volume": 522837, "name": "NIFTY10FEB2626350CE", "token": "42564", "SR Low -": 26344.75, "SR Low +": 26355.25, "SR PC -": 26342.35, "SR PC +": 26357.65, "SR High -": 26339.7, "SR High +": 26360.3}, {"06.02.2026": "Call26450", "instrumentType": "Index Options", "expiryDate": "10-Feb-2026", "optionType": "Call", "strikePrice": "26450", "openPrice": 9.1, "highPrice": 9.1, "lowPrice": 4.25, "closePrice": 6.25, "volume": 480492, "name": "NIFTY10FEB2626450CE", "token": "42568", "SR Low -": 26445.75, "SR Low +": 26454.25, "SR PC -": 26443.75, "SR PC +": 26456.25, "SR High -": 26440.9, "SR High +": 26459.1}, {"06.02.2026": "Put24600", "instrumentType": "Index Options", "expiryDate": "10-Feb-2026", "optionType": "Put", "strikePrice": "24600", "openPrice": 6.75, "highPrice": 8.05, "lowPrice": 4.75, "closePrice": 7.1, "volume": 473078, "name": "NIFTY10FEB2624600PE", "token": "42481", "SR Low -": 24595.25, "SR Low +": 24604.75, "SR PC -": 24592.9, "SR PC +": 24607.1, "SR High -": 24591.95, "SR High +": 24608.05}, {"06.02.2026": "Put24200", "instrumentType": "Index Options", "expiryDate": "10-Feb-2026", "optionType": "Put", "strikePrice": "24200", "openPrice": 3.4, "highPrice": 5.0, "lowPrice": 2.65, "closePrice": 4.4, "volume": 467366, "name": "NIFTY10FEB2624200PE", "token": "42451", "SR Low -": 24197.35, "SR Low +": 24202.65, "SR PC -": 24195.6, "SR PC +": 24204.4, "SR High -": 24195.0, "SR High +": 24205.0}, {"06.02.2026": "Put24700", "instrumentType": "Index Options", "expiryDate": "10-Feb-2026", "optionType": "Put", "strikePrice": "24700", "openPrice": 8.1, "highPrice": 9.15, "lowPrice": 5.45, "closePrice": 8.1, "volume": 458804, "name": "NIFTY10FEB2624700PE", "token": "42487", "SR Low -": 24694.55, "SR Low +": 24705.45, "SR PC -": 24691.9, "SR PC +": 24708.1, "SR High -": 24690.85, "SR High +": 24709.15}, {"06.02.2026": "Call26900", "instrumentType": "Index Options", "expiryDate": "10-Feb-2026", "optionType": "Call", "strikePrice": "26900", "openPrice": 3.7, "highPrice": 3.75, "lowPrice": 1.95, "closePrice": 2.6, "volume": 458085, "name": "NIFTY10FEB2626900CE", "token": "42590", "SR Low -": 26898.05, "SR Low +": 26901.95, "SR PC -": 26897.4, "SR PC +": 26902.6, "SR High -": 26896.25, "SR High +": 26903.75}, {"06.02.2026": "Call27500", "instrumentType": "Index Options", "expiryDate": "10-Feb-2026", "optionType": "Call", "strikePrice": "27500", "openPrice": 1.5, "highPrice": 1.7, "lowPrice": 1.1, "closePrice": 1.2, "volume": 447955, "name": "NIFTY10FEB2627500CE", "token": "42622", "SR Low -": 27498.9, "SR Low +": 27501.1, "SR PC -": 27498.8, "SR PC +": 27501.2, "SR High -": 27498.3, "SR High +": 27501.7}, {"06.02.2026": "Put23500", "instrumentType": "Index Options", "expiryDate": "10-Feb-2026", "optionType": "Put", "strikePrice": "23500", "openPrice": 1.75, "highPrice": 2.75, "lowPrice": 1.45, "closePrice": 2.45, "volume": 426970, "name": "NIFTY10FEB2623500PE", "token": "42411", "SR Low -": 23498.55, "SR Low +": 23501.45, "SR PC -": 23497.55, "SR PC +": 23502.45, "SR High -": 23497.25, "SR High +": 23502.75}, {"06.02.2026": "Put24400", "instrumentType": "Index Options", "expiryDate": "10-Feb-2026", "optionType": "Put", "strikePrice": "24400", "openPrice": 5.5, "highPrice": 6.25, "lowPrice": 3.1, "closePrice": 5.5, "volume": 426266, "name": "NIFTY10FEB2624400PE", "token": "42469", "SR Low -": 24396.9, "SR Low +": 24403.1, "SR PC -": 24394.5, "SR PC +": 24405.5, "SR High -": 24393.75, "SR High +": 24406.25}, {"06.02.2026": "Put24850", "instrumentType": "Index Options", "expiryDate": "10-Feb-2026", "optionType": "Put", "strikePrice": "24850", "openPrice": 11.2, "highPrice": 11.2, "lowPrice": 6.85, "closePrice": 9.6, "volume": 408842, "name": "NIFTY10FEB2624850PE", "token": "42493", "SR Low -": 24843.15, "SR Low +": 24856.85, "SR PC -": 24840.4, "SR PC +": 24859.6, "SR High -": 24838.8, "SR High +": 24861.2}, {"06.02.2026": "Put25050", "instrumentType": "Index Options", "expiryDate": "10-Feb-2026", "optionType": "Put", "strikePrice": "25050", "openPrice": 17.5, "highPrice": 17.5, "lowPrice": 9.4, "closePrice": 12.3, "volume": 381976, "name": "NIFTY10FEB2625050PE", "token": "42503", "SR Low -": 25040.6, "SR Low +": 25059.4, "SR PC -": 25037.7, "SR PC +": 25062.3, "SR High -": 25032.5, "SR High +": 25067.5}, {"06.02.2026": "Put24950", "instrumentType": "Index Options", "expiryDate": "10-Feb-2026", "optionType": "Put", "strikePrice": "24950", "openPrice": 12.9, "highPrice": 13.3, "lowPrice": 8.05, "closePrice": 10.85, "volume": 357481, "name": "NIFTY10FEB2624950PE", "token": "42499", "SR Low -": 24941.95, "SR Low +": 24958.05, "SR PC -": 24939.15, "SR PC +": 24960.85, "SR High -": 24936.7, "SR High +": 24963.3}, {"06.02.2026": "Call27200", "instrumentType": "Index Options", "expiryDate": "10-Feb-2026", "optionType": "Call", "strikePrice": "27200", "openPrice": 2.05, "highPrice": 2.2, "lowPrice": 1.25, "closePrice": 1.45, "volume": 327063, "name": "NIFTY10FEB2627200CE", "token": "42610", "SR Low -": 27198.75, "SR Low +": 27201.25, "SR PC -": 27198.55, "SR PC +": 27201.45, "SR High -": 27197.8, "SR High +": 27202.2}, {"06.02.2026": "Put24300", "instrumentType": "Index Options", "expiryDate": "10-Feb-2026", "optionType": "Put", "strikePrice": "24300", "openPrice": 4.85, "highPrice": 5.65, "lowPrice": 3.1, "closePrice": 4.95, "volume": 322033, "name": "NIFTY10FEB2624300PE", "token": "42463", "SR Low -": 24296.9, "SR Low +": 24303.1, "SR PC -": 24295.05, "SR PC +": 24304.95, "SR High -": 24294.35, "SR High +": 24305.65}, {"06.02.2026": "Call26650", "instrumentType": "Index Options", "expiryDate": "10-Feb-2026", "optionType": "Call", "strikePrice": "26650", "openPrice": 4.6, "highPrice": 5.95, "lowPrice": 3.05, "closePrice": 4.25, "volume": 306130, "name": "NIFTY10FEB2626650CE", "token": "42578", "SR Low -": 26646.95, "SR Low +": 26653.05, "SR PC -": 26645.75, "SR PC +": 26654.25, "SR High -": 26644.05, "SR High +": 26655.95}, {"06.02.2026": "Put24100", "instrumentType": "Index Options", "expiryDate": "10-Feb-2026", "optionType": "Put", "strikePrice": "24100", "openPrice": 3.65, "highPrice": 4.6, "lowPrice": 2.45, "closePrice": 4.15, "volume": 300429, "name": "NIFTY10FEB2624100PE", "token": "42447", "SR Low -": 24097.55, "SR Low +": 24102.45, "SR PC -": 24095.85, "SR PC +": 24104.15, "SR High -": 24095.4, "SR High +": 24104.6}, {"06.02.2026": "Put23100", "instrumentType": "Index Options", "expiryDate": "10-Feb-2026", "optionType": "Put", "strikePrice": "23100", "openPrice": 1.6, "highPrice": 2.2, "lowPrice": 1.15, "closePrice": 1.95, "volume": 294715, "name": "NIFTY10FEB2623100PE", "token": "42391", "SR Low -": 23098.85, "SR Low +": 23101.15, "SR PC -": 23098.05, "SR PC +": 23101.95, "SR High -": 23097.8, "SR High +": 23102.2}, {"06.02.2026": "Call26750", "instrumentType": "Index Options", "expiryDate": "10-Feb-2026", "optionType": "Call", "strikePrice": "26750", "openPrice": 5.2, "highPrice": 5.2, "lowPrice": 2.55, "closePrice": 3.5, "volume": 293713, "name": "NIFTY10FEB2626750CE", "token": "42582", "SR Low -": 26747.45, "SR Low +": 26752.55, "SR PC -": 26746.5, "SR PC +": 26753.5, "SR High -": 26744.8, "SR High +": 26755.2}, {"06.02.2026": "Put24550", "instrumentType": "Index Options", "expiryDate": "10-Feb-2026", "optionType": "Put", "strikePrice": "24550", "openPrice": 6.0, "highPrice": 7.55, "lowPrice": 4.45, "closePrice": 6.7, "volume": 285871, "name": "NIFTY10FEB2624550PE", "token": "42479", "SR Low -": 24545.55, "SR Low +": 24554.45, "SR PC -": 24543.3, "SR PC +": 24556.7, "SR High -": 24542.45, "SR High +": 24557.55}, {"06.02.2026": "Put24750", "instrumentType": "Index Options", "expiryDate": "10-Feb-2026", "optionType": "Put", "strikePrice": "24750", "openPrice": 8.15, "highPrice": 9.6, "lowPrice": 5.9, "closePrice": 8.55, "volume": 281931, "name": "NIFTY10FEB2624750PE", "token": "42489", "SR Low -": 24744.1, "SR Low +": 24755.9, "SR PC -": 24741.45, "SR PC +": 24758.55, "SR High -": 24740.4, "SR High +": 24759.6}, {"06.02.2026": "Call27100", "instrumentType": "Index Options", "expiryDate": "10-Feb-2026", "optionType": "Call", "strikePrice": "27100", "openPrice": 2.7, "highPrice": 2.7, "lowPrice": 1.4, "closePrice": 1.7, "volume": 277120, "name": "NIFTY10FEB2627100CE", "token": "42606", "SR Low -": 27098.6, "SR Low +": 27101.4, "SR PC -": 27098.3, "SR PC +": 27101.7, "SR High -": 27097.3, "SR High +": 27102.7}, {"06.02.2026": "Call26850", "instrumentType": "Index Options", "expiryDate": "10-Feb-2026", "optionType": "Call", "strikePrice": "26850", "openPrice": 3.2, "highPrice": 4.1, "lowPrice": 2.2, "closePrice": 2.75, "volume": 259989, "name": "NIFTY10FEB2626850CE", "token": "42588", "SR Low -": 26847.8, "SR Low +": 26852.2, "SR PC -": 26847.25, "SR PC +": 26852.75, "SR High -": 26845.9, "SR High +": 26854.1}, {"06.02.2026": "Put24650", "instrumentType": "Index Options", "expiryDate": "10-Feb-2026", "optionType": "Put", "strikePrice": "24650", "openPrice": 7.0, "highPrice": 8.5, "lowPrice": 5.1, "closePrice": 7.55, "volume": 247097, "name": "NIFTY10FEB2624650PE", "token": "42483", "SR Low -": 24644.9, "SR Low +": 24655.1, "SR PC -": 24642.45, "SR PC +": 24657.55, "SR High -": 24641.5, "SR High +": 24658.5}, {"06.02.2026": "Put23800", "instrumentType": "Index Options", "expiryDate": "10-Feb-2026", "optionType": "Put", "strikePrice": "23800", "openPrice": 2.2, "highPrice": 3.45, "lowPrice": 1.7, "closePrice": 3.05, "volume": 218732, "name": "NIFTY10FEB2623800PE", "token": "42429", "SR Low -": 23798.3, "SR Low +": 23801.7, "SR PC -": 23796.95, "SR PC +": 23803.05, "SR High -": 23796.55, "SR High +": 23803.45}, {"06.02.2026": "Put24250", "instrumentType": "Index Options", "expiryDate": "10-Feb-2026", "optionType": "Put", "strikePrice": "24250", "openPrice": 3.9, "highPrice": 5.35, "lowPrice": 2.9, "closePrice": 4.8, "volume": 214660, "name": "NIFTY10FEB2624250PE", "token": "42457", "SR Low -": 24247.1, "SR Low +": 24252.9, "SR PC -": 24245.2, "SR PC +": 24254.8, "SR High -": 24244.65, "SR High +": 24255.35}, {"06.02.2026": "Call27400", "instrumentType": "Index Options", "expiryDate": "10-Feb-2026", "optionType": "Call", "strikePrice": "27400", "openPrice": 1.7, "highPrice": 1.8, "lowPrice": 1.1, "closePrice": 1.3, "volume": 200217, "name": "NIFTY10FEB2627400CE", "token": "42618", "SR Low -": 27398.9, "SR Low +": 27401.1, "SR PC -": 27398.7, "SR PC +": 27401.3, "SR High -": 27398.2, "SR High +": 27401.8}, {"06.02.2026": "Put24150", "instrumentType": "Index Options", "expiryDate": "10-Feb-2026", "optionType": "Put", "strikePrice": "24150", "openPrice": 3.5, "highPrice": 4.9, "lowPrice": 2.55, "closePrice": 4.3, "volume": 196335, "name": "NIFTY10FEB2624150PE", "token": "42449", "SR Low -": 24147.45, "SR Low +": 24152.55, "SR PC -": 24145.7, "SR PC +": 24154.3, "SR High -": 24145.1, "SR High +": 24154.9}, {"06.02.2026": "Call25300", "instrumentType": "Index Options", "expiryDate": "10-Feb-2026", "optionType": "Call", "strikePrice": "25300", "openPrice": 346.0, "highPrice": 403.65, "lowPrice": 244.0, "closePrice": 394.35, "volume": 196122, "name": "NIFTY10FEB2625300CE", "token": "42512", "SR Low -": 25056.0, "SR Low +": 25544.0, "SR PC -": 24905.65, "SR PC +": 25694.35, "SR High -": 24896.35, "SR High +": 25703.65}, {"06.02.2026": "Call26950", "instrumentType": "Index Options", "expiryDate": "10-Feb-2026", "optionType": "Call", "strikePrice": "26950", "openPrice": 2.85, "highPrice": 3.25, "lowPrice": 1.75, "closePrice": 2.25, "volume": 158870, "name": "NIFTY10FEB2626950CE", "token": "42596", "SR Low -": 26948.25, "SR Low +": 26951.75, "SR PC -": 26947.75, "SR PC +": 26952.25, "SR High -": 26946.75, "SR High +": 26953.25}, {"06.02.2026": "Call27300", "instrumentType": "Index Options", "expiryDate": "10-Feb-2026", "optionType": "Call", "strikePrice": "27300", "openPrice": 1.7, "highPrice": 1.95, "lowPrice": 1.15, "closePrice": 1.35, "volume": 153897, "name": "NIFTY10FEB2627300CE", "token": "42614", "SR Low -": 27298.85, "SR Low +": 27301.15, "SR PC -": 27298.65, "SR PC +": 27301.35, "SR High -": 27298.05, "SR High +": 27301.95}, {"06.02.2026": "Call27050", "instrumentType": "Index Options", "expiryDate": "10-Feb-2026", "optionType": "Call", "strikePrice": "27050", "openPrice": 2.6, "highPrice": 2.6, "lowPrice": 1.5, "closePrice": 1.9, "volume": 152075, "name": "NIFTY10FEB2627050CE", "token": "42602", "SR Low -": 27048.5, "SR Low +": 27051.5, "SR PC -": 27048.1, "SR PC +": 27051.9, "SR High -": 27047.4, "SR High +": 27052.6}, {"06.02.2026": "Put23700", "instrumentType": "Index Options", "expiryDate": "10-Feb-2026", "optionType": "Put", "strikePrice": "23700", "openPrice": 1.9, "highPrice": 3.3, "lowPrice": 1.4, "closePrice": 2.8, "volume": 149346, "name": "NIFTY10FEB2623700PE", "token": "42419", "SR Low -": 23698.6, "SR Low +": 23701.4, "SR PC -": 23697.2, "SR PC +": 23702.8, "SR High -": 23696.7, "SR High +": 23703.3}, {"06.02.2026": "Put25900", "instrumentType": "Index Options", "expiryDate": "10-Feb-2026", "optionType": "Put", "strikePrice": "25900", "openPrice": 349.35, "highPrice": 415.0, "lowPrice": 245.25, "closePrice": 255.8, "volume": 149141, "name": "NIFTY10FEB2625900PE", "token": "42543", "SR Low -": 25654.75, "SR Low +": 26145.25, "SR PC -": 25644.2, "SR PC +": 26155.8, "SR High -": 25485.0, "SR High +": 26315.0}, {"06.02.2026": "Put23900", "instrumentType": "Index Options", "expiryDate": "10-Feb-2026", "optionType": "Put", "strikePrice": "23900", "openPrice": 2.45, "highPrice": 3.8, "lowPrice": 1.85, "closePrice": 3.35, "volume": 143630, "name": "NIFTY10FEB2623900PE", "token": "42433", "SR Low -": 23898.15, "SR Low +": 23901.85, "SR PC -": 23896.65, "SR PC +": 23903.35, "SR High -": 23896.2, "SR High +": 23903.8}, {"06.02.2026": "Put24450", "instrumentType": "Index Options", "expiryDate": "10-Feb-2026", "optionType": "Put", "strikePrice": "24450", "openPrice": 5.3, "highPrice": 6.7, "lowPrice": 3.95, "closePrice": 5.9, "volume": 137194, "name": "NIFTY10FEB2624450PE", "token": "42471", "SR Low -": 24446.05, "SR Low +": 24453.95, "SR PC -": 24444.1, "SR PC +": 24455.9, "SR High -": 24443.3, "SR High +": 24456.7}, {"06.02.2026": "Put24050", "instrumentType": "Index Options", "expiryDate": "10-Feb-2026", "optionType": "Put", "strikePrice": "24050", "openPrice": 3.0, "highPrice": 4.4, "lowPrice": 2.1, "closePrice": 3.85, "volume": 137004, "name": "NIFTY10FEB2624050PE", "token": "42445", "SR Low -": 24047.9, "SR Low +": 24052.1, "SR PC -": 24046.15, "SR PC +": 24053.85, "SR High -": 24045.6, "SR High +": 24054.4}, {"06.02.2026": "Put23600", "instrumentType": "Index Options", "expiryDate": "10-Feb-2026", "optionType": "Put", "strikePrice": "23600", "openPrice": 2.0, "highPrice": 3.0, "lowPrice": 1.4, "closePrice": 2.65, "volume": 136215, "name": "NIFTY10FEB2623600PE", "token": "42415", "SR Low -": 23598.6, "SR Low +": 23601.4, "SR PC -": 23597.35, "SR PC +": 23602.65, "SR High -": 23597.0, "SR High +": 23603.0}, {"06.02.2026": "Put26000", "instrumentType": "Index Options", "expiryDate": "10-Feb-2026", "optionType": "Put", "strikePrice": "26000", "openPrice": 418.0, "highPrice": 512.0, "lowPrice": 332.55, "closePrice": 344.25, "volume": 131178, "name": "NIFTY10FEB2626000PE", "token": "42547", "SR Low -": 25667.45, "SR Low +": 26332.55, "SR PC -": 25655.75, "SR PC +": 26344.25, "SR High -": 25488.0, "SR High +": 26512.0}, {"06.02.2026": "Put23400", "instrumentType": "Index Options", "expiryDate": "10-Feb-2026", "optionType": "Put", "strikePrice": "23400", "openPrice": 1.75, "highPrice": 2.7, "lowPrice": 1.35, "closePrice": 2.4, "volume": 126410, "name": "NIFTY10FEB2623400PE", "token": "42407", "SR Low -": 23398.65, "SR Low +": 23401.35, "SR PC -": 23397.6, "SR PC +": 23402.4, "SR High -": 23397.3, "SR High +": 23402.7}, {"06.02.2026": "Put24350", "instrumentType": "Index Options", "expiryDate": "10-Feb-2026", "optionType": "Put", "strikePrice": "24350", "openPrice": 4.55, "highPrice": 5.95, "lowPrice": 3.35, "closePrice": 5.3, "volume": 125773, "name": "NIFTY10FEB2624350PE", "token": "42467", "SR Low -": 24346.65, "SR Low +": 24353.35, "SR PC -": 24344.7, "SR PC +": 24355.3, "SR High -": 24344.05, "SR High +": 24355.95}, {"06.02.2026": "Call27950", "instrumentType": "Index Options", "expiryDate": "10-Feb-2026", "optionType": "Call", "strikePrice": "27950", "openPrice": 1.25, "highPrice": 1.3, "lowPrice": 0.9, "closePrice": 1.0, "volume": 123486, "name": "NIFTY10FEB2627950CE", "token": "42640", "SR Low -": 27949.1, "SR Low +": 27950.9, "SR PC -": 27949.0, "SR PC +": 27951.0, "SR High -": 27948.7, "SR High +": 27951.3}, {"06.02.2026": "Call27900", "instrumentType": "Index Options", "expiryDate": "10-Feb-2026", "optionType": "Call", "strikePrice": "27900", "openPrice": 1.25, "highPrice": 1.25, "lowPrice": 0.85, "closePrice": 1.05, "volume": 119589, "name": "NIFTY10FEB2627900CE", "token": "42638", "SR Low -": 27899.15, "SR Low +": 27900.85, "SR PC -": 27898.95, "SR PC +": 27901.05, "SR High -": 27898.75, "SR High +": 27901.25}, {"06.02.2026": "Put23300", "instrumentType": "Index Options", "expiryDate": "10-Feb-2026", "optionType": "Put", "strikePrice": "23300", "openPrice": 1.8, "highPrice": 2.5, "lowPrice": 1.3, "closePrice": 2.15, "volume": 111414, "name": "NIFTY10FEB2623300PE", "token": "42401", "SR Low -": 23298.7, "SR Low +": 23301.3, "SR PC -": 23297.85, "SR PC +": 23302.15, "SR High -": 23297.5, "SR High +": 23302.5}, {"06.02.2026": "Call27150", "instrumentType": "Index Options", "expiryDate": "10-Feb-2026", "optionType": "Call", "strikePrice": "27150", "openPrice": 2.2, "highPrice": 2.35, "lowPrice": 1.4, "closePrice": 1.65, "volume": 109520, "name": "NIFTY10FEB2627150CE", "token": "42608", "SR Low -": 27148.6, "SR Low +": 27151.4, "SR PC -": 27148.35, "SR PC +": 27151.65, "SR High -": 27147.65, "SR High +": 27152.35}, {"06.02.2026": "Call25350", "instrumentType": "Index Options", "expiryDate": "10-Feb-2026", "optionType": "Call", "strikePrice": "25350", "openPrice": 300.0, "highPrice": 357.0, "lowPrice": 206.55, "closePrice": 347.85, "volume": 108098, "name": "NIFTY10FEB2625350CE", "token": "42514", "SR Low -": 25143.45, "SR Low +": 25556.55, "SR PC -": 25002.15, "SR PC +": 25697.85, "SR High -": 24993.0, "SR High +": 25707.0}, {"06.02.2026": "Put25850", "instrumentType": "Index Options", "expiryDate": "10-Feb-2026", "optionType": "Put", "strikePrice": "25850", "openPrice": 299.95, "highPrice": 370.0, "lowPrice": 205.2, "closePrice": 214.85, "volume": 105815, "name": "NIFTY10FEB2625850PE", "token": "42539", "SR Low -": 25644.8, "SR Low +": 26055.2, "SR PC -": 25635.15, "SR PC +": 26064.85, "SR High -": 25480.0, "SR High +": 26220.0}, {"06.02.2026": "Put23200", "instrumentType": "Index Options", "expiryDate": "10-Feb-2026", "optionType": "Put", "strikePrice": "23200", "openPrice": 1.55, "highPrice": 2.35, "lowPrice": 1.2, "closePrice": 2.1, "volume": 92577, "name": "NIFTY10FEB2623200PE", "token": "42395", "SR Low -": 23198.8, "SR Low +": 23201.2, "SR PC -": 23197.9, "SR PC +": 23202.1, "SR High -": 23197.65, "SR High +": 23202.35}, {"06.02.2026": "Put23550", "instrumentType": "Index Options", "expiryDate": "10-Feb-2026", "optionType": "Put", "strikePrice": "23550", "openPrice": 1.85, "highPrice": 2.85, "lowPrice": 1.5, "closePrice": 2.55, "volume": 92097, "name": "NIFTY10FEB2623550PE", "token": "42413", "SR Low -": 23548.5, "SR Low +": 23551.5, "SR PC -": 23547.45, "SR PC +": 23552.55, "SR High -": 23547.15, "SR High +": 23552.85}, {"06.02.2026": "Call27800", "instrumentType": "Index Options", "expiryDate": "10-Feb-2026", "optionType": "Call", "strikePrice": "27800", "openPrice": 1.4, "highPrice": 1.5, "lowPrice": 0.9, "closePrice": 1.1, "volume": 89746, "name": "NIFTY10FEB2627800CE", "token": "42634", "SR Low -": 27799.1, "SR Low +": 27800.9, "SR PC -": 27798.9, "SR PC +": 27801.1, "SR High -": 27798.5, "SR High +": 27801.5}, {"06.02.2026": "Call27600", "instrumentType": "Index Options", "expiryDate": "10-Feb-2026", "optionType": "Call", "strikePrice": "27600", "openPrice": 1.6, "highPrice": 1.65, "lowPrice": 1.05, "closePrice": 1.2, "volume": 89396, "name": "NIFTY10FEB2627600CE", "token": "42626", "SR Low -": 27598.95, "SR Low +": 27601.05, "SR PC -": 27598.8, "SR PC +": 27601.2, "SR High -": 27598.35, "SR High +": 27601.65}, {"06.02.2026": "Put23150", "instrumentType": "Index Options", "expiryDate": "10-Feb-2026", "optionType": "Put", "strikePrice": "23150", "openPrice": 1.3, "highPrice": 2.2, "lowPrice": 1.1, "closePrice": 2.0, "volume": 86236, "name": "NIFTY10FEB2623150PE", "token": "42393", "SR Low -": 23148.9, "SR Low +": 23151.1, "SR PC -": 23148.0, "SR PC +": 23152.0, "SR High -": 23147.8, "SR High +": 23152.2}, {"06.02.2026": "Call27250", "instrumentType": "Index Options", "expiryDate": "10-Feb-2026", "optionType": "Call", "strikePrice": "27250", "openPrice": 2.15, "highPrice": 2.15, "lowPrice": 1.3, "closePrice": 1.5, "volume": 85433, "name": "NIFTY10FEB2627250CE", "token": "42612", "SR Low -": 27248.7, "SR Low +": 27251.3, "SR PC -": 27248.5, "SR PC +": 27251.5, "SR High -": 27247.85, "SR High +": 27252.15}, {"06.02.2026": "Call27700", "instrumentType": "Index Options", "expiryDate": "10-Feb-2026", "optionType": "Call", "strikePrice": "27700", "openPrice": 1.45, "highPrice": 1.55, "lowPrice": 1.0, "closePrice": 1.2, "volume": 85323, "name": "NIFTY10FEB2627700CE", "token": "42630", "SR Low -": 27699.0, "SR Low +": 27701.0, "SR PC -": 27698.8, "SR PC +": 27701.2, "SR High -": 27698.45, "SR High +": 27701.55}, {"06.02.2026": "Put23750", "instrumentType": "Index Options", "expiryDate": "10-Feb-2026", "optionType": "Put", "strikePrice": "23750", "openPrice": 2.15, "highPrice": 3.35, "lowPrice": 1.75, "closePrice": 2.95, "volume": 84232, "name": "NIFTY10FEB2623750PE", "token": "42423", "SR Low -": 23748.25, "SR Low +": 23751.75, "SR PC -": 23747.05, "SR PC +": 23752.95, "SR High -": 23746.65, "SR High +": 23753.35}, {"06.02.2026": "Put23850", "instrumentType": "Index Options", "expiryDate": "10-Feb-2026", "optionType": "Put", "strikePrice": "23850", "openPrice": 2.35, "highPrice": 3.7, "lowPrice": 1.85, "closePrice": 3.2, "volume": 78607, "name": "NIFTY10FEB2623850PE", "token": "42431", "SR Low -": 23848.15, "SR Low +": 23851.85, "SR PC -": 23846.8, "SR PC +": 23853.2, "SR High -": 23846.3, "SR High +": 23853.7}, {"06.02.2026": "Put23950", "instrumentType": "Index Options", "expiryDate": "10-Feb-2026", "optionType": "Put", "strikePrice": "23950", "openPrice": 2.75, "highPrice": 4.0, "lowPrice": 2.05, "closePrice": 3.5, "volume": 76494, "name": "NIFTY10FEB2623950PE", "token": "42437", "SR Low -": 23947.95, "SR Low +": 23952.05, "SR PC -": 23946.5, "SR PC +": 23953.5, "SR High -": 23946.0, "SR High +": 23954.0}, {"06.02.2026": "Put23650", "instrumentType": "Index Options", "expiryDate": "10-Feb-2026", "optionType": "Put", "strikePrice": "23650", "openPrice": 2.0, "highPrice": 3.1, "lowPrice": 1.45, "closePrice": 2.75, "volume": 76379, "name": "NIFTY10FEB2623650PE", "token": "42417", "SR Low -": 23648.55, "SR Low +": 23651.45, "SR PC -": 23647.25, "SR PC +": 23652.75, "SR High -": 23646.9, "SR High +": 23653.1}, {"06.02.2026": "Call27550", "instrumentType": "Index Options", "expiryDate": "10-Feb-2026", "optionType": "Call", "strikePrice": "27550", "openPrice": 1.8, "highPrice": 1.8, "lowPrice": 1.05, "closePrice": 1.3, "volume": 69165, "name": "NIFTY10FEB2627550CE", "token": "42624", "SR Low -": 27548.95, "SR Low +": 27551.05, "SR PC -": 27548.7, "SR PC +": 27551.3, "SR High -": 27548.2, "SR High +": 27551.8}, {"06.02.2026": "Call27350", "instrumentType": "Index Options", "expiryDate": "10-Feb-2026", "optionType": "Call", "strikePrice": "27350", "openPrice": 1.6, "highPrice": 1.95, "lowPrice": 1.15, "closePrice": 1.4, "volume": 66961, "name": "NIFTY10FEB2627350CE", "token": "42616", "SR Low -": 27348.85, "SR Low +": 27351.15, "SR PC -": 27348.6, "SR PC +": 27351.4, "SR High -": 27348.05, "SR High +": 27351.95}, {"06.02.2026": "Put23250", "instrumentType": "Index Options", "expiryDate": "10-Feb-2026", "optionType": "Put", "strikePrice": "23250", "openPrice": 1.85, "highPrice": 5.3, "lowPrice": 1.25, "closePrice": 2.15, "volume": 63937, "name": "NIFTY10FEB2623250PE", "token": "42399", "SR Low -": 23248.75, "SR Low +": 23251.25, "SR PC -": 23247.85, "SR PC +": 23252.15, "SR High -": 23244.7, "SR High +": 23255.3}, {"06.02.2026": "Call27450", "instrumentType": "Index Options", "expiryDate": "10-Feb-2026", "optionType": "Call", "strikePrice": "27450", "openPrice": 1.55, "highPrice": 1.8, "lowPrice": 1.1, "closePrice": 1.3, "volume": 62821, "name": "NIFTY10FEB2627450CE", "token": "42620", "SR Low -": 27448.9, "SR Low +": 27451.1, "SR PC -": 27448.7, "SR PC +": 27451.3, "SR High -": 27448.2, "SR High +": 27451.8}, {"06.02.2026": "Put23450", "instrumentType": "Index Options", "expiryDate": "10-Feb-2026", "optionType": "Put", "strikePrice": "23450", "openPrice": 1.8, "highPrice": 2.75, "lowPrice": 1.25, "closePrice": 2.4, "volume": 62385, "name": "NIFTY10FEB2623450PE", "token": "42409", "SR Low -": 23448.75, "SR Low +": 23451.25, "SR PC -": 23447.6, "SR PC +": 23452.4, "SR High -": 23447.25, "SR High +": 23452.75}, {"06.02.2026": "Put23350", "instrumentType": "Index Options", "expiryDate": "10-Feb-2026", "optionType": "Put", "strikePrice": "23350", "openPrice": 1.4, "highPrice": 2.65, "lowPrice": 1.4, "closePrice": 2.35, "volume": 62106, "name": "NIFTY10FEB2623350PE", "token": "42405", "SR Low -": 23348.6, "SR Low +": 23351.4, "SR PC -": 23347.65, "SR PC +": 23352.35, "SR High -": 23347.35, "SR High +": 23352.65}, {"06.02.2026": "Call27850", "instrumentType": "Index Options", "expiryDate": "10-Feb-2026", "optionType": "Call", "strikePrice": "27850", "openPrice": 1.55, "highPrice": 1.55, "lowPrice": 0.9, "closePrice": 1.05, "volume": 50053, "name": "NIFTY10FEB2627850CE", "token": "42636", "SR Low -": 27849.1, "SR Low +": 27850.9, "SR PC -": 27848.95, "SR PC +": 27851.05, "SR High -": 27848.45, "SR High +": 27851.55}, {"06.02.2026": "Call25200", "instrumentType": "Index Options", "expiryDate": "10-Feb-2026", "optionType": "Call", "strikePrice": "25200", "openPrice": 430.0, "highPrice": 499.5, "lowPrice": 329.0, "closePrice": 490.8, "volume": 44552, "name": "NIFTY10FEB2625200CE", "token": "42508", "SR Low -": 24871.0, "SR Low +": 25529.0, "SR PC -": 24709.2, "SR PC +": 25690.8, "SR High -": 24700.5, "SR High +": 25699.5}, {"06.02.2026": "Call27650", "instrumentType": "Index Options", "expiryDate": "10-Feb-2026", "optionType": "Call", "strikePrice": "27650", "openPrice": 1.5, "highPrice": 1.55, "lowPrice": 1.05, "closePrice": 1.25, "volume": 42641, "name": "NIFTY10FEB2627650CE", "token": "42628", "SR Low -": 27648.95, "SR Low +": 27651.05, "SR PC -": 27648.75, "SR PC +": 27651.25, "SR High -": 27648.45, "SR High +": 27651.55}, {"06.02.2026": "Call25000", "instrumentType": "Index Options", "expiryDate": "10-Feb-2026", "optionType": "Call", "strikePrice": "25000", "openPrice": 652.6, "highPrice": 695.35, "lowPrice": 513.45, "closePrice": 686.6, "volume": 31531, "name": "NIFTY10FEB2625000CE", "token": "42500", "SR Low -": 24486.55, "SR Low +": 25513.45, "SR PC -": 24313.4, "SR PC +": 25686.6, "SR High -": 24304.65, "SR High +": 25695.35}, {"06.02.2026": "Put25950", "instrumentType": "Index Options", "expiryDate": "10-Feb-2026", "optionType": "Put", "strikePrice": "25950", "openPrice": 380.0, "highPrice": 462.0, "lowPrice": 287.9, "closePrice": 298.7, "volume": 31134, "name": "NIFTY10FEB2625950PE", "token": "42545", "SR Low -": 25662.1, "SR Low +": 26237.9, "SR PC -": 25651.3, "SR PC +": 26248.7, "SR High -": 25488.0, "SR High +": 26412.0}, {"06.02.2026": "Call27750", "instrumentType": "Index Options", "expiryDate": "10-Feb-2026", "optionType": "Call", "strikePrice": "27750", "openPrice": 1.55, "highPrice": 1.6, "lowPrice": 0.95, "closePrice": 1.2, "volume": 29637, "name": "NIFTY10FEB2627750CE", "token": "42632", "SR Low -": 27749.05, "SR Low +": 27750.95, "SR PC -": 27748.8, "SR PC +": 27751.2, "SR High -": 27748.4, "SR High +": 27751.6}, {"06.02.2026": "Call25250", "instrumentType": "Index Options", "expiryDate": "10-Feb-2026", "optionType": "Call", "strikePrice": "25250", "openPrice": 361.75, "highPrice": 451.5, "lowPrice": 285.0, "closePrice": 441.45, "volume": 22600, "name": "NIFTY10FEB2625250CE", "token": "42510", "SR Low -": 24965.0, "SR Low +": 25535.0, "SR PC -": 24808.55, "SR PC +": 25691.45, "SR High -": 24798.5, "SR High +": 25701.5}, {"06.02.2026": "Call25100", "instrumentType": "Index Options", "expiryDate": "10-Feb-2026", "optionType": "Call", "strikePrice": "25100", "openPrice": 502.0, "highPrice": 595.4, "lowPrice": 417.95, "closePrice": 586.7, "volume": 14162, "name": "NIFTY10FEB2625100CE", "token": "42504", "SR Low -": 24682.05, "SR Low +": 25517.95, "SR PC -": 24513.3, "SR PC +": 25686.7, "SR High -": 24504.6, "SR High +": 25695.4}, {"06.02.2026": "Put26100", "instrumentType": "Index Options", "expiryDate": "10-Feb-2026", "optionType": "Put", "strikePrice": "26100", "openPrice": 530.95, "highPrice": 606.0, "lowPrice": 426.15, "closePrice": 437.75, "volume": 12268, "name": "NIFTY10FEB2626100PE", "token": "42555", "SR Low -": 25673.85, "SR Low +": 26526.15, "SR PC -": 25662.25, "SR PC +": 26537.75, "SR High -": 25494.0, "SR High +": 26706.0}, {"06.02.2026": "Put26300", "instrumentType": "Index Options", "expiryDate": "10-Feb-2026", "optionType": "Put", "strikePrice": "26300", "openPrice": 732.4, "highPrice": 798.2, "lowPrice": 624.0, "closePrice": 632.3, "volume": 8080, "name": "NIFTY10FEB2626300PE", "token": "42563", "SR Low -": 25676.0, "SR Low +": 26924.0, "SR PC -": 25667.7, "SR PC +": 26932.3, "SR High -": 25501.8, "SR High +": 27098.2}, {"06.02.2026": "Call25150", "instrumentType": "Index Options", "expiryDate": "10-Feb-2026", "optionType": "Call", "strikePrice": "25150", "openPrice": 432.8, "highPrice": 548.0, "lowPrice": 373.4, "closePrice": 538.75, "volume": 6741, "name": "NIFTY10FEB2625150CE", "token": "42506", "SR Low -": 24776.6, "SR Low +": 25523.4, "SR PC -": 24611.25, "SR PC +": 25688.75, "SR High -": 24602.0, "SR High +": 25698.0}, {"06.02.2026": "Put26200", "instrumentType": "Index Options", "expiryDate": "10-Feb-2026", "optionType": "Put", "strikePrice": "26200", "openPrice": 639.95, "highPrice": 703.2, "lowPrice": 522.1, "closePrice": 535.4, "volume": 5771, "name": "NIFTY10FEB2626200PE", "token": "42559", "SR Low -": 25677.9, "SR Low +": 26722.1, "SR PC -": 25664.6, "SR PC +": 26735.4, "SR High -": 25496.8, "SR High +": 26903.2}, {"06.02.2026": "Put26500", "instrumentType": "Index Options", "expiryDate": "10-Feb-2026", "optionType": "Put", "strikePrice": "26500", "openPrice": 924.1, "highPrice": 1000.0, "lowPrice": 818.0, "closePrice": 828.2, "volume": 5536, "name": "NIFTY10FEB2626500PE", "token": "42571", "SR Low -": 25682.0, "SR Low +": 27318.0, "SR PC -": 25671.8, "SR PC +": 27328.2, "SR High -": 25500.0, "SR High +": 27500.0}, {"06.02.2026": "Put26050", "instrumentType": "Index Options", "expiryDate": "10-Feb-2026", "optionType": "Put", "strikePrice": "26050", "openPrice": 482.35, "highPrice": 555.0, "lowPrice": 379.3, "closePrice": 391.0, "volume": 3650, "name": "NIFTY10FEB2626050PE", "token": "42551", "SR Low -": 25670.7, "SR Low +": 26429.3, "SR PC -": 25659.0, "SR PC +": 26441.0, "SR High -": 25495.0, "SR High +": 26605.0}, {"06.02.2026": "Call24900", "instrumentType": "Index Options", "expiryDate": "10-Feb-2026", "optionType": "Call", "strikePrice": "24900", "openPrice": 708.6, "highPrice": 793.3, "lowPrice": 609.75, "closePrice": 783.95, "volume": 2310, "name": "NIFTY10FEB2624900CE", "token": "42494", "SR Low -": 24290.25, "SR Low +": 25509.75, "SR PC -": 24116.05, "SR PC +": 25683.95, "SR High -": 24106.7, "SR High +": 25693.3}, {"06.02.2026": "Call24500", "instrumentType": "Index Options", "expiryDate": "10-Feb-2026", "optionType": "Call", "strikePrice": "24500", "openPrice": 1087.95, "highPrice": 1190.0, "lowPrice": 1007.95, "closePrice": 1182.2, "volume": 2157, "name": "NIFTY10FEB2624500CE", "token": "42472", "SR Low -": 23492.05, "SR Low +": 25507.95, "SR PC -": 23317.8, "SR PC +": 25682.2, "SR High -": 23310.0, "SR High +": 25690.0}, {"06.02.2026": "Put26150", "instrumentType": "Index Options", "expiryDate": "10-Feb-2026", "optionType": "Put", "strikePrice": "26150", "openPrice": 571.4, "highPrice": 652.15, "lowPrice": 475.95, "closePrice": 484.9, "volume": 1605, "name": "NIFTY10FEB2626150PE", "token": "42557", "SR Low -": 25674.05, "SR Low +": 26625.95, "SR PC -": 25665.1, "SR PC +": 26634.9, "SR High -": 25497.85, "SR High +": 26802.15}, {"06.02.2026": "Call24800", "instrumentType": "Index Options", "expiryDate": "10-Feb-2026", "optionType": "Call", "strikePrice": "24800", "openPrice": 813.75, "highPrice": 891.4, "lowPrice": 708.6, "closePrice": 886.45, "volume": 1474, "name": "NIFTY10FEB2624800CE", "token": "42490", "SR Low -": 24091.4, "SR Low +": 25508.6, "SR PC -": 23913.55, "SR PC +": 25686.45, "SR High -": 23908.6, "SR High +": 25691.4}, {"06.02.2026": "Call25050", "instrumentType": "Index Options", "expiryDate": "10-Feb-2026", "optionType": "Call", "strikePrice": "25050", "openPrice": 560.0, "highPrice": 644.35, "lowPrice": 470.2, "closePrice": 635.65, "volume": 1452, "name": "NIFTY10FEB2625050CE", "token": "42502", "SR Low -": 24579.8, "SR Low +": 25520.2, "SR PC -": 24414.35, "SR PC +": 25685.65, "SR High -": 24405.65, "SR High +": 25694.35}, {"06.02.2026": "Call24950", "instrumentType": "Index Options", "expiryDate": "10-Feb-2026", "optionType": "Call", "strikePrice": "24950", "openPrice": 659.55, "highPrice": 736.95, "lowPrice": 562.75, "closePrice": 733.0, "volume": 984, "name": "NIFTY10FEB2624950CE", "token": "42498", "SR Low -": 24387.25, "SR Low +": 25512.75, "SR PC -": 24217.0, "SR PC +": 25683.0, "SR High -": 24213.05, "SR High +": 25686.95}, {"06.02.2026": "Put26400", "instrumentType": "Index Options", "expiryDate": "10-Feb-2026", "optionType": "Put", "strikePrice": "26400", "openPrice": 825.0, "highPrice": 898.4, "lowPrice": 722.95, "closePrice": 728.05, "volume": 932, "name": "NIFTY10FEB2626400PE", "token": "42567", "SR Low -": 25677.05, "SR Low +": 27122.95, "SR PC -": 25671.95, "SR PC +": 27128.05, "SR High -": 25501.6, "SR High +": 27298.4}, {"06.02.2026": "Put26550", "instrumentType": "Index Options", "expiryDate": "10-Feb-2026", "optionType": "Put", "strikePrice": "26550", "openPrice": 1009.3, "highPrice": 1034.95, "lowPrice": 875.3, "closePrice": 880.7, "volume": 686, "name": "NIFTY10FEB2626550PE", "token": "42575", "SR Low -": 25674.7, "SR Low +": 27425.3, "SR PC -": 25669.3, "SR PC +": 27430.7, "SR High -": 25515.05, "SR High +": 27584.95}, {"06.02.2026": "Call24700", "instrumentType": "Index Options", "expiryDate": "10-Feb-2026", "optionType": "Call", "strikePrice": "24700", "openPrice": 900.0, "highPrice": 992.1, "lowPrice": 812.15, "closePrice": 983.7, "volume": 505, "name": "NIFTY10FEB2624700CE", "token": "42484", "SR Low -": 23887.85, "SR Low +": 25512.15, "SR PC -": 23716.3, "SR PC +": 25683.7, "SR High -": 23707.9, "SR High +": 25692.1}, {"06.02.2026": "Put27000", "instrumentType": "Index Options", "expiryDate": "10-Feb-2026", "optionType": "Put", "strikePrice": "27000", "openPrice": 1368.05, "highPrice": 1492.1, "lowPrice": 1319.5, "closePrice": 1326.5, "volume": 463, "name": "NIFTY10FEB2627000PE", "token": "42601", "SR Low -": 25680.5, "SR Low +": 28319.5, "SR PC -": 25673.5, "SR PC +": 28326.5, "SR High -": 25507.9, "SR High +": 28492.1}, {"06.02.2026": "Call24850", "instrumentType": "Index Options", "expiryDate": "10-Feb-2026", "optionType": "Call", "strikePrice": "24850", "openPrice": 774.0, "highPrice": 835.7, "lowPrice": 665.95, "closePrice": 834.4, "volume": 423, "name": "NIFTY10FEB2624850CE", "token": "42492", "SR Low -": 24184.05, "SR Low +": 25515.95, "SR PC -": 24015.6, "SR PC +": 25684.4, "SR High -": 24014.3, "SR High +": 25685.7}, {"06.02.2026": "Put26250", "instrumentType": "Index Options", "expiryDate": "10-Feb-2026", "optionType": "Put", "strikePrice": "26250", "openPrice": 644.3, "highPrice": 746.65, "lowPrice": 578.0, "closePrice": 584.1, "volume": 355, "name": "NIFTY10FEB2626250PE", "token": "42561", "SR Low -": 25672.0, "SR Low +": 26828.0, "SR PC -": 25665.9, "SR PC +": 26834.1, "SR High -": 25503.35, "SR High +": 26996.65}, {"06.02.2026": "Put26350", "instrumentType": "Index Options", "expiryDate": "10-Feb-2026", "optionType": "Put", "strikePrice": "26350", "openPrice": 752.05, "highPrice": 841.65, "lowPrice": 675.0, "closePrice": 681.85, "volume": 313, "name": "NIFTY10FEB2626350PE", "token": "42565", "SR Low -": 25675.0, "SR Low +": 27025.0, "SR PC -": 25668.15, "SR PC +": 27031.85, "SR High -": 25508.35, "SR High +": 27191.65}, {"06.02.2026": "Call24000", "instrumentType": "Index Options", "expiryDate": "10-Feb-2026", "optionType": "Call", "strikePrice": "24000", "openPrice": 1594.0, "highPrice": 1680.95, "lowPrice": 1519.45, "closePrice": 1673.45, "volume": 298, "name": "NIFTY10FEB2624000CE", "token": "42438", "SR Low -": 22480.55, "SR Low +": 25519.45, "SR PC -": 22326.55, "SR PC +": 25673.45, "SR High -": 22319.05, "SR High +": 25680.95}, {"06.02.2026": "Call24600", "instrumentType": "Index Options", "expiryDate": "10-Feb-2026", "optionType": "Call", "strikePrice": "24600", "openPrice": 1037.9, "highPrice": 1085.95, "lowPrice": 915.1, "closePrice": 1080.35, "volume": 181, "name": "NIFTY10FEB2624600CE", "token": "42480", "SR Low -": 23684.9, "SR Low +": 25515.1, "SR PC -": 23519.65, "SR PC +": 25680.35, "SR High -": 23514.05, "SR High +": 25685.95}, {"06.02.2026": "Put26600", "instrumentType": "Index Options", "expiryDate": "10-Feb-2026", "optionType": "Put", "strikePrice": "26600", "openPrice": 981.8, "highPrice": 1098.4, "lowPrice": 918.4, "closePrice": 919.9, "volume": 155, "name": "NIFTY10FEB2626600PE", "token": "42577", "SR Low -": 25681.6, "SR Low +": 27518.4, "SR PC -": 25680.1, "SR PC +": 27519.9, "SR High -": 25501.6, "SR High +": 27698.4}, {"06.02.2026": "Put26700", "instrumentType": "Index Options", "expiryDate": "10-Feb-2026", "optionType": "Put", "strikePrice": "26700", "openPrice": 1100.0, "highPrice": 1167.05, "lowPrice": 1019.25, "closePrice": 1024.5, "volume": 108, "name": "NIFTY10FEB2626700PE", "token": "42581", "SR Low -": 25680.75, "SR Low +": 27719.25, "SR PC -": 25675.5, "SR PC +": 27724.5, "SR High -": 25532.95, "SR High +": 27867.05}, {"06.02.2026": "Call24400", "instrumentType": "Index Options", "expiryDate": "10-Feb-2026", "optionType": "Call", "strikePrice": "24400", "openPrice": 1125.1, "highPrice": 1285.5, "lowPrice": 1113.1, "closePrice": 1278.4, "volume": 74, "name": "NIFTY10FEB2624400CE", "token": "42468", "SR Low -": 23286.9, "SR Low +": 25513.1, "SR PC -": 23121.6, "SR PC +": 25678.4, "SR High -": 23114.5, "SR High +": 25685.5}, {"06.02.2026": "Put26450", "instrumentType": "Index Options", "expiryDate": "10-Feb-2026", "optionType": "Put", "strikePrice": "26450", "openPrice": 850.5, "highPrice": 930.0, "lowPrice": 778.15, "closePrice": 780.55, "volume": 73, "name": "NIFTY10FEB2626450PE", "token": "42569", "SR Low -": 25671.85, "SR Low +": 27228.15, "SR PC -": 25669.45, "SR PC +": 27230.55, "SR High -": 25520.0, "SR High +": 27380.0}, {"06.02.2026": "Call24750", "instrumentType": "Index Options", "expiryDate": "10-Feb-2026", "optionType": "Call", "strikePrice": "24750", "openPrice": 825.0, "highPrice": 930.05, "lowPrice": 766.0, "closePrice": 930.05, "volume": 64, "name": "NIFTY10FEB2624750CE", "token": "42488", "SR Low -": 23984.0, "SR Low +": 25516.0, "SR PC -": 23819.95, "SR PC +": 25680.05, "SR High -": 23819.95, "SR High +": 25680.05}, {"06.02.2026": "Put26650", "instrumentType": "Index Options", "expiryDate": "10-Feb-2026", "optionType": "Put", "strikePrice": "26650", "openPrice": 1035.0, "highPrice": 1089.45, "lowPrice": 979.2, "closePrice": 979.8, "volume": 60, "name": "NIFTY10FEB2626650PE", "token": "42579", "SR Low -": 25670.8, "SR Low +": 27629.2, "SR PC -": 25670.2, "SR PC +": 27629.8, "SR High -": 25560.55, "SR High +": 27739.45}, {"06.02.2026": "Call23100", "instrumentType": "Index Options", "expiryDate": "10-Feb-2026", "optionType": "Call", "strikePrice": "23100", "openPrice": 2445.0, "highPrice": 2544.35, "lowPrice": 2445.0, "closePrice": 2520.0, "volume": 53, "name": "NIFTY10FEB2623100CE", "token": "42390", "SR Low -": 20655.0, "SR Low +": 25545.0, "SR PC -": 20580.0, "SR PC +": 25620.0, "SR High -": 20555.65, "SR High +": 25644.35}, {"06.02.2026": "Call24650", "instrumentType": "Index Options", "expiryDate": "10-Feb-2026", "optionType": "Call", "strikePrice": "24650", "openPrice": 917.85, "highPrice": 1040.0, "lowPrice": 879.6, "closePrice": 1037.5, "volume": 41, "name": "NIFTY10FEB2624650CE", "token": "42482", "SR Low -": 23770.4, "SR Low +": 25529.6, "SR PC -": 23612.5, "SR PC +": 25687.5, "SR High -": 23610.0, "SR High +": 25690.0}, {"06.02.2026": "Call24550", "instrumentType": "Index Options", "expiryDate": "10-Feb-2026", "optionType": "Call", "strikePrice": "24550", "openPrice": 1023.95, "highPrice": 1135.15, "lowPrice": 960.0, "closePrice": 1131.65, "volume": 32, "name": "NIFTY10FEB2624550CE", "token": "42476", "SR Low -": 23590.0, "SR Low +": 25510.0, "SR PC -": 23418.35, "SR PC +": 25681.65, "SR High -": 23414.85, "SR High +": 25685.15}, {"06.02.2026": "Put26900", "instrumentType": "Index Options", "expiryDate": "10-Feb-2026", "optionType": "Put", "strikePrice": "26900", "openPrice": 1266.95, "highPrice": 1351.0, "lowPrice": 1230.45, "closePrice": 1230.9, "volume": 22, "name": "NIFTY10FEB2626900PE", "token": "42595", "SR Low -": 25669.55, "SR Low +": 28130.45, "SR PC -": 25669.1, "SR PC +": 28130.9, "SR High -": 25549.0, "SR High +": 28251.0}, {"06.02.2026": "Call24300", "instrumentType": "Index Options", "expiryDate": "10-Feb-2026", "optionType": "Call", "strikePrice": "24300", "openPrice": 1301.1, "highPrice": 1384.75, "lowPrice": 1220.5, "closePrice": 1380.4, "volume": 20, "name": "NIFTY10FEB2624300CE", "token": "42458", "SR Low -": 23079.5, "SR Low +": 25520.5, "SR PC -": 22919.6, "SR PC +": 25680.4, "SR High -": 22915.25, "SR High +": 25684.75}, {"06.02.2026": "Put26800", "instrumentType": "Index Options", "expiryDate": "10-Feb-2026", "optionType": "Put", "strikePrice": "26800", "openPrice": 1231.0, "highPrice": 1264.8, "lowPrice": 1119.9, "closePrice": 1119.9, "volume": 19, "name": "NIFTY10FEB2626800PE", "token": "42587", "SR Low -": 25680.1, "SR Low +": 27919.9, "SR PC -": 25680.1, "SR PC +": 27919.9, "SR High -": 25535.2, "SR High +": 28064.8}, {"06.02.2026": "Put26750", "instrumentType": "Index Options", "expiryDate": "10-Feb-2026", "optionType": "Put", "strikePrice": "26750", "openPrice": 1220.35, "highPrice": 1220.35, "lowPrice": 1070.5, "closePrice": 1076.6, "volume": 18, "name": "NIFTY10FEB2626750PE", "token": "42583", "SR Low -": 25679.5, "SR Low +": 27820.5, "SR PC -": 25673.4, "SR PC +": 27826.6, "SR High -": 25529.65, "SR High +": 27970.35}, {"06.02.2026": "Call23500", "instrumentType": "Index Options", "expiryDate": "10-Feb-2026", "optionType": "Call", "strikePrice": "23500", "openPrice": 2132.15, "highPrice": 2185.0, "lowPrice": 2025.0, "closePrice": 2173.2, "volume": 14, "name": "NIFTY10FEB2623500CE", "token": "42410", "SR Low -": 21475.0, "SR Low +": 25525.0, "SR PC -": 21326.8, "SR PC +": 25673.2, "SR High -": 21315.0, "SR High +": 25685.0}, {"06.02.2026": "Call24200", "instrumentType": "Index Options", "expiryDate": "10-Feb-2026", "optionType": "Call", "strikePrice": "24200", "openPrice": 1360.0, "highPrice": 1461.95, "lowPrice": 1360.0, "closePrice": 1461.95, "volume": 11, "name": "NIFTY10FEB2624200CE", "token": "42450", "SR Low -": 22840.0, "SR Low +": 25560.0, "SR PC -": 22738.05, "SR PC +": 25661.95, "SR High -": 22738.05, "SR High +": 25661.95}, {"06.02.2026": "Put27500", "instrumentType": "Index Options", "expiryDate": "10-Feb-2026", "optionType": "Put", "strikePrice": "27500", "openPrice": 1950.0, "highPrice": 1950.0, "lowPrice": 1817.35, "closePrice": 1817.35, "volume": 10, "name": "NIFTY10FEB2627500PE", "token": "42623", "SR Low -": 25682.65, "SR Low +": 29317.35, "SR PC -": 25682.65, "SR PC +": 29317.35, "SR High -": 25550.0, "SR High +": 29450.0}, {"06.02.2026": "Call24100", "instrumentType": "Index Options", "expiryDate": "10-Feb-2026", "optionType": "Call", "strikePrice": "24100", "openPrice": 1440.7, "highPrice": 1549.35, "lowPrice": 1417.0, "closePrice": 1540.0, "volume": 8, "name": "NIFTY10FEB2624100CE", "token": "42446", "SR Low -": 22683.0, "SR Low +": 25517.0, "SR PC -": 22560.0, "SR PC +": 25640.0, "SR High -": 22550.65, "SR High +": 25649.35}, {"06.02.2026": "Call23300", "instrumentType": "Index Options", "expiryDate": "10-Feb-2026", "optionType": "Call", "strikePrice": "23300", "openPrice": 2250.0, "highPrice": 2314.9, "lowPrice": 2250.0, "closePrice": 2314.9, "volume": 5, "name": "NIFTY10FEB2623300CE", "token": "42400", "SR Low -": 21050.0, "SR Low +": 25550.0, "SR PC -": 20985.1, "SR PC +": 25614.9, "SR High -": 20985.1, "SR High +": 25614.9}, {"06.02.2026": "Call23600", "instrumentType": "Index Options", "expiryDate": "10-Feb-2026", "optionType": "Call", "strikePrice": "23600", "openPrice": 1979.05, "highPrice": 2025.0, "lowPrice": 1963.95, "closePrice": 2025.0, "volume": 5, "name": "NIFTY10FEB2623600CE", "token": "42414", "SR Low -": 21636.05, "SR Low +": 25563.95, "SR PC -": 21575.0, "SR PC +": 25625.0, "SR High -": 21575.0, "SR High +": 25625.0}, {"06.02.2026": "Call23700", "instrumentType": "Index Options", "expiryDate": "10-Feb-2026", "optionType": "Call", "strikePrice": "23700", "openPrice": 1925.0, "highPrice": 1930.0, "lowPrice": 1864.1, "closePrice": 1920.0, "volume": 5, "name": "NIFTY10FEB2623700CE", "token": "42418", "SR Low -": 21835.9, "SR Low +": 25564.1, "SR PC -": 21780.0, "SR PC +": 25620.0, "SR High -": 21770.0, "SR High +": 25630.0}, {"06.02.2026": "Put27100", "instrumentType": "Index Options", "expiryDate": "10-Feb-2026", "optionType": "Put", "strikePrice": "27100", "openPrice": 1480.0, "highPrice": 1513.35, "lowPrice": 1468.65, "closePrice": 1468.7, "volume": 4, "name": "NIFTY10FEB2627100PE", "token": "42607", "SR Low -": 25631.35, "SR Low +": 28568.65, "SR PC -": 25631.3, "SR PC +": 28568.7, "SR High -": 25586.65, "SR High +": 28613.35}, {"06.02.2026": "Call24350", "instrumentType": "Index Options", "expiryDate": "10-Feb-2026", "optionType": "Call", "strikePrice": "24350", "openPrice": 1300.0, "highPrice": 1300.0, "lowPrice": 1197.0, "closePrice": 1233.1, "volume": 4, "name": "NIFTY10FEB2624350CE", "token": "42464", "SR Low -": 23153.0, "SR Low +": 25547.0, "SR PC -": 23116.9, "SR PC +": 25583.1, "SR High -": 23050.0, "SR High +": 25650.0}, {"06.02.2026": "Call24450", "instrumentType": "Index Options", "expiryDate": "10-Feb-2026", "optionType": "Call", "strikePrice": "24450", "openPrice": 1073.85, "highPrice": 1206.05, "lowPrice": 1073.85, "closePrice": 1206.05, "volume": 4, "name": "NIFTY10FEB2624450CE", "token": "42470", "SR Low -": 23376.15, "SR Low +": 25523.85, "SR PC -": 23243.95, "SR PC +": 25656.05, "SR High -": 23243.95, "SR High +": 25656.05}, {"06.02.2026": "Call23400", "instrumentType": "Index Options", "expiryDate": "10-Feb-2026", "optionType": "Call", "strikePrice": "23400", "openPrice": 2165.0, "highPrice": 2220.0, "lowPrice": 2165.0, "closePrice": 2220.0, "volume": 4, "name": "NIFTY10FEB2623400CE", "token": "42406", "SR Low -": 21235.0, "SR Low +": 25565.0, "SR PC -": 21180.0, "SR PC +": 25620.0, "SR High -": 21180.0, "SR High +": 25620.0}, {"06.02.2026": "Call23900", "instrumentType": "Index Options", "expiryDate": "10-Feb-2026", "optionType": "Call", "strikePrice": "23900", "openPrice": 1672.8, "highPrice": 1736.0, "lowPrice": 1672.8, "closePrice": 1736.0, "volume": 4, "name": "NIFTY10FEB2623900CE", "token": "42432", "SR Low -": 22227.2, "SR Low +": 25572.8, "SR PC -": 22164.0, "SR PC +": 25636.0, "SR High -": 22164.0, "SR High +": 25636.0}, {"06.02.2026": "Call23200", "instrumentType": "Index Options", "expiryDate": "10-Feb-2026", "optionType": "Call", "strikePrice": "23200", "openPrice": 2350.0, "highPrice": 2425.0, "lowPrice": 2350.0, "closePrice": 2425.0, "volume": 4, "name": "NIFTY10FEB2623200CE", "token": "42394", "SR Low -": 20850.0, "SR Low +": 25550.0, "SR PC -": 20775.0, "SR PC +": 25625.0, "SR High -": 20775.0, "SR High +": 25625.0}, {"06.02.2026": "Put27950", "instrumentType": "Index Options", "expiryDate": "10-Feb-2026", "optionType": "Put", "strikePrice": "27950", "openPrice": 2383.0, "highPrice": 2395.8, "lowPrice": 2308.0, "closePrice": 2395.8, "volume": 3, "name": "NIFTY10FEB2627950PE", "token": "42645", "SR Low -": 25642.0, "SR Low +": 30258.0, "SR PC -": 25554.2, "SR PC +": 30345.8, "SR High -": 25554.2, "SR High +": 30345.8}, {"06.02.2026": "Call24150", "instrumentType": "Index Options", "expiryDate": "10-Feb-2026", "optionType": "Call", "strikePrice": "24150", "openPrice": 1424.5, "highPrice": 1424.5, "lowPrice": 1424.5, "closePrice": 1424.5, "volume": 2, "name": "NIFTY10FEB2624150CE", "token": "42448", "SR Low -": 22725.5, "SR Low +": 25574.5, "SR PC -": 22725.5, "SR PC +": 25574.5, "SR High -": 22725.5, "SR High +": 25574.5}, {"06.02.2026": "Put27800", "instrumentType": "Index Options", "expiryDate": "10-Feb-2026", "optionType": "Put", "strikePrice": "27800", "openPrice": 2220.0, "highPrice": 2230.0, "lowPrice": 2220.0, "closePrice": 2230.0, "volume": 2, "name": "NIFTY10FEB2627800PE", "token": "42635", "SR Low -": 25580.0, "SR Low +": 30020.0, "SR PC -": 25570.0, "SR PC +": 30030.0, "SR High -": 25570.0, "SR High +": 30030.0}, {"06.02.2026": "Call24250", "instrumentType": "Index Options", "expiryDate": "10-Feb-2026", "optionType": "Call", "strikePrice": "24250", "openPrice": 1275.15, "highPrice": 1370.25, "lowPrice": 1275.15, "closePrice": 1370.25, "volume": 2, "name": "NIFTY10FEB2624250CE", "token": "42452", "SR Low -": 22974.85, "SR Low +": 25525.15, "SR PC -": 22879.75, "SR PC +": 25620.25, "SR High -": 22879.75, "SR High +": 25620.25}, {"06.02.2026": "Call23850", "instrumentType": "Index Options", "expiryDate": "10-Feb-2026", "optionType": "Call", "strikePrice": "23850", "openPrice": 1769.35, "highPrice": 1769.35, "lowPrice": 1769.35, "closePrice": 1769.35, "volume": 1, "name": "NIFTY10FEB2623850CE", "token": "42430", "SR Low -": 22080.65, "SR Low +": 25619.35, "SR PC -": 22080.65, "SR PC +": 25619.35, "SR High -": 22080.65, "SR High +": 25619.35}, {"06.02.2026": "Call23750", "instrumentType": "Index Options", "expiryDate": "10-Feb-2026", "optionType": "Call", "strikePrice": "23750", "openPrice": 1894.6, "highPrice": 1894.6, "lowPrice": 1894.6, "closePrice": 1894.6, "volume": 1, "name": "NIFTY10FEB2623750CE", "token": "42420", "SR Low -": 21855.4, "SR Low +": 25644.6, "SR PC -": 21855.4, "SR PC +": 25644.6, "SR High -": 21855.4, "SR High +": 25644.6}, {"06.02.2026": "Call23800", "instrumentType": "Index Options", "expiryDate": "10-Feb-2026", "optionType": "Call", "strikePrice": "23800", "openPrice": 1825.0, "highPrice": 1825.0, "lowPrice": 1825.0, "closePrice": 1825.0, "volume": 1, "name": "NIFTY10FEB2623800CE", "token": "42424", "SR Low -": 21975.0, "SR Low +": 25625.0, "SR PC -": 21975.0, "SR PC +": 25625.0, "SR High -": 21975.0, "SR High +": 25625.0}, {"06.02.2026": "Call23650", "instrumentType": "Index Options", "expiryDate": "10-Feb-2026", "optionType": "Call", "strikePrice": "23650", "openPrice": 1969.05, "highPrice": 1969.05, "lowPrice": 1969.05, "closePrice": 1969.05, "volume": 1, "name": "NIFTY10FEB2623650CE", "token": "42416", "SR Low -": 21680.95, "SR Low +": 25619.05, "SR PC -": 21680.95, "SR PC +": 25619.05, "SR High -": 21680.95, "SR High +": 25619.05}, {"06.02.2026": "Put27550", "instrumentType": "Index Options", "expiryDate": "10-Feb-2026", "optionType": "Put", "strikePrice": "27550", "openPrice": 1948.0, "highPrice": 1948.0, "lowPrice": 1948.0, "closePrice": 1948.0, "volume": 1, "name": "NIFTY10FEB2627550PE", "token": "42625", "SR Low -": 25602.0, "SR Low +": 29498.0, "SR PC -": 25602.0, "SR PC +": 29498.0, "SR High -": 25602.0, "SR High +": 29498.0}, {"06.02.2026": "Put26950", "instrumentType": "Index Options", "expiryDate": "10-Feb-2026", "optionType": "Put", "strikePrice": "26950", "openPrice": "-", "highPrice": "-", "lowPrice": "-", "closePrice": "-", "volume": 0, "name": "NIFTY10FEB2626950PE", "token": "42599", "SR Low -": "", "SR Low +": "", "SR PC -": "", "SR PC +": "", "SR High -": "", "SR High +": ""}, {"06.02.2026": "Put27200", "instrumentType": "Index Options", "expiryDate": "10-Feb-2026", "optionType": "Put", "strikePrice": "27200", "openPrice": "-", "highPrice": "-", "lowPrice": "-", "closePrice": "-", "volume": 0, "name": "NIFTY10FEB2627200PE", "token": "42611", "SR Low -": "", "SR Low +": "", "SR PC -": "", "SR PC +": "", "SR High -": "", "SR High +": ""}, {"06.02.2026": "Put27750", "instrumentType": "Index Options", "expiryDate": "10-Feb-2026", "optionType": "Put", "strikePrice": "27750", "openPrice": "-", "highPrice": "-", "lowPrice": "-", "closePrice": "-", "volume": 0, "name": "NIFTY10FEB2627750PE", "token": "42633", "SR Low -": "", "SR Low +": "", "SR PC -": "", "SR PC +": "", "SR High -": "", "SR High +": ""}, {"06.02.2026": "Call23950", "instrumentType": "Index Options", "expiryDate": "10-Feb-2026", "optionType": "Call", "strikePrice": "23950", "openPrice": "-", "highPrice": "-", "lowPrice": "-", "closePrice": "-", "volume": 0, "name": "NIFTY10FEB2623950CE", "token": "42434", "SR Low -": "", "SR Low +": "", "SR PC -": "", "SR PC +": "", "SR High -": "", "SR High +": ""}, {"06.02.2026": "Put26850", "instrumentType": "Index Options", "expiryDate": "10-Feb-2026", "optionType": "Put", "strikePrice": "26850", "openPrice": "-", "highPrice": "-", "lowPrice": "-", "closePrice": "-", "volume": 0, "name": "NIFTY10FEB2626850PE", "token": "42589", "SR Low -": "", "SR Low +": "", "SR PC -": "", "SR PC +": "", "SR High -": "", "SR High +": ""}, {"06.02.2026": "Put27050", "instrumentType": "Index Options", "expiryDate": "10-Feb-2026", "optionType": "Put", "strikePrice": "27050", "openPrice": "-", "highPrice": "-", "lowPrice": "-", "closePrice": "-", "volume": 0, "name": "NIFTY10FEB2627050PE", "token": "42605", "SR Low -": "", "SR Low +": "", "SR PC -": "", "SR PC +": "", "SR High -": "", "SR High +": ""}, {"06.02.2026": "Put27700", "instrumentType": "Index Options", "expiryDate": "10-Feb-2026", "optionType": "Put", "strikePrice": "27700", "openPrice": "-", "highPrice": "-", "lowPrice": "-", "closePrice": "-", "volume": 0, "name": "NIFTY10FEB2627700PE", "token": "42631", "SR Low -": "", "SR Low +": "", "SR PC -": "", "SR PC +": "", "SR High -": "", "SR High +": ""}, {"06.02.2026": "Call23550", "instrumentType": "Index Options", "expiryDate": "10-Feb-2026", "optionType": "Call", "strikePrice": "23550", "openPrice": "-", "highPrice": "-", "lowPrice": "-", "closePrice": "-", "volume": 0, "name": "NIFTY10FEB2623550CE", "token": "42412", "SR Low -": "", "SR Low +": "", "SR PC -": "", "SR PC +": "", "SR High -": "", "SR High +": ""}, {"06.02.2026": "Put27350", "instrumentType": "Index Options", "expiryDate": "10-Feb-2026", "optionType": "Put", "strikePrice": "27350", "openPrice": "-", "highPrice": "-", "lowPrice": "-", "closePrice": "-", "volume": 0, "name": "NIFTY10FEB2627350PE", "token": "42617", "SR Low -": "", "SR Low +": "", "SR PC -": "", "SR PC +": "", "SR High -": "", "SR High +": ""}, {"06.02.2026": "Call23250", "instrumentType": "Index Options", "expiryDate": "10-Feb-2026", "optionType": "Call", "strikePrice": "23250", "openPrice": "-", "highPrice": "-", "lowPrice": "-", "closePrice": "-", "volume": 0, "name": "NIFTY10FEB2623250CE", "token": "42396", "SR Low -": "", "SR Low +": "", "SR PC -": "", "SR PC +": "", "SR High -": "", "SR High +": ""}, {"06.02.2026": "Call23350", "instrumentType": "Index Options", "expiryDate": "10-Feb-2026", "optionType": "Call", "strikePrice": "23350", "openPrice": "-", "highPrice": "-", "lowPrice": "-", "closePrice": "-", "volume": 0, "name": "NIFTY10FEB2623350CE", "token": "42402", "SR Low -": "", "SR Low +": "", "SR PC -": "", "SR PC +": "", "SR High -": "", "SR High +": ""}, {"06.02.2026": "Put27250", "instrumentType": "Index Options", "expiryDate": "10-Feb-2026", "optionType": "Put", "strikePrice": "27250", "openPrice": "-", "highPrice": "-", "lowPrice": "-", "closePrice": "-", "volume": 0, "name": "NIFTY10FEB2627250PE", "token": "42613", "SR Low -": "", "SR Low +": "", "SR PC -": "", "SR PC +": "", "SR High -": "", "SR High +": ""}, {"06.02.2026": "Put27900", "instrumentType": "Index Options", "expiryDate": "10-Feb-2026", "optionType": "Put", "strikePrice": "27900", "openPrice": "-", "highPrice": "-", "lowPrice": "-", "closePrice": "-", "volume": 0, "name": "NIFTY10FEB2627900PE", "token": "42639", "SR Low -": "", "SR Low +": "", "SR PC -": "", "SR PC +": "", "SR High -": "", "SR High +": ""}, {"06.02.2026": "Call23150", "instrumentType": "Index Options", "expiryDate": "10-Feb-2026", "optionType": "Call", "strikePrice": "23150", "openPrice": "-", "highPrice": "-", "lowPrice": "-", "closePrice": "-", "volume": 0, "name": "NIFTY10FEB2623150CE", "token": "42392", "SR Low -": "", "SR Low +": "", "SR PC -": "", "SR PC +": "", "SR High -": "", "SR High +": ""}, {"06.02.2026": "Call24050", "instrumentType": "Index Options", "expiryDate": "10-Feb-2026", "optionType": "Call", "strikePrice": "24050", "openPrice": "-", "highPrice": "-", "lowPrice": "-", "closePrice": "-", "volume": 0, "name": "NIFTY10FEB2624050CE", "token": "42442", "SR Low -": "", "SR Low +": "", "SR PC -": "", "SR PC +": "", "SR High -": "", "SR High +": ""}, {"06.02.2026": "Put27300", "instrumentType": "Index Options", "expiryDate": "10-Feb-2026", "optionType": "Put", "strikePrice": "27300", "openPrice": "-", "highPrice": "-", "lowPrice": "-", "closePrice": "-", "volume": 0, "name": "NIFTY10FEB2627300PE", "token": "42615", "SR Low -": "", "SR Low +": "", "SR PC -": "", "SR PC +": "", "SR High -": "", "SR High +": ""}, {"06.02.2026": "Put27850", "instrumentType": "Index Options", "expiryDate": "10-Feb-2026", "optionType": "Put", "strikePrice": "27850", "openPrice": "-", "highPrice": "-", "lowPrice": "-", "closePrice": "-", "volume": 0, "name": "NIFTY10FEB2627850PE", "token": "42637", "SR Low -": "", "SR Low +": "", "SR PC -": "", "SR PC +": "", "SR High -": "", "SR High +": ""}, {"06.02.2026": "Put27400", "instrumentType": "Index Options", "expiryDate": "10-Feb-2026", "optionType": "Put", "strikePrice": "27400", "openPrice": "-", "highPrice": "-", "lowPrice": "-", "closePrice": "-", "volume": 0, "name": "NIFTY10FEB2627400PE", "token": "42619", "SR Low -": "", "SR Low +": "", "SR PC -": "", "SR PC +": "", "SR High -": "", "SR High +": ""}, {"06.02.2026": "Put27600", "instrumentType": "Index Options", "expiryDate": "10-Feb-2026", "optionType": "Put", "strikePrice": "27600", "openPrice": "-", "highPrice": "-", "lowPrice": "-", "closePrice": "-", "volume": 0, "name": "NIFTY10FEB2627600PE", "token": "42627", "SR Low -": "", "SR Low +": "", "SR PC -": "", "SR PC +": "", "SR High -": "", "SR High +": ""}, {"06.02.2026": "Call23450", "instrumentType": "Index Options", "expiryDate": "10-Feb-2026", "optionType": "Call", "strikePrice": "23450", "openPrice": "-", "highPrice": "-", "lowPrice": "-", "closePrice": "-", "volume": 0, "name": "NIFTY10FEB2623450CE", "token": "42408", "SR Low -": "", "SR Low +": "", "SR PC -": "", "SR PC +": "", "SR High -": "", "SR High +": ""}, {"06.02.2026": "Put27150", "instrumentType": "Index Options", "expiryDate": "10-Feb-2026", "optionType": "Put", "strikePrice": "27150", "openPrice": "-", "highPrice": "-", "lowPrice": "-", "closePrice": "-", "volume": 0, "name": "NIFTY10FEB2627150PE", "token": "42609", "SR Low -": "", "SR Low +": "", "SR PC -": "", "SR PC +": "", "SR High -": "", "SR High +": ""}, {"06.02.2026": "Put27650", "instrumentType": "Index Options", "expiryDate": "10-Feb-2026", "optionType": "Put", "strikePrice": "27650", "openPrice": "-", "highPrice": "-", "lowPrice": "-", "closePrice": "-", "volume": 0, "name": "NIFTY10FEB2627650PE", "token": "42629", "SR Low -": "", "SR Low +": "", "SR PC -": "", "SR PC +": "", "SR High -": "", "SR High +": ""}, {"06.02.2026": "Put27450", "instrumentType": "Index Options", "expiryDate": "10-Feb-2026", "optionType": "Put", "strikePrice": "27450", "openPrice": "-", "highPrice": "-", "lowPrice": "-", "closePrice": "-", "volume": 0, "name": "NIFTY10FEB2627450PE", "token": "42621", "SR Low -": "", "SR Low +": "", "SR PC -": "", "SR PC +": "", "SR High -": "", "SR High +": ""}]